{
	"id": "bcdd6d8b-6a5f-42a0-9afe-46f469684451",
	"name": "TwitterEnv",
	"values": [
		{
			"key": "APIKey",
			"value": "",
			"enabled": true
		},
		{
			"key": "APISecretKey",
			"value": "",
			"enabled": true
		},
		{
			"key": "AccessToken",
			"value": "",
			"enabled": true
		},
		{
			"key": "AccessTokenSecret",
			"value": "",
			"enabled": true
		},
		{
			"key": "Name[0]",
			"value": "",
			"enabled": true
		},
		{
			"key": "Location[0]",
			"value": "",
			"enabled": true
		},
		{
			"key": "ScreenName[0]",
			"value": "",
			"enabled": true
		},
		{
			"key": "Description[0]",
			"value": "",
			"enabled": true
		},
		{
			"key": "Name[1]",
			"value": "",
			"enabled": true
		},
		{
			"key": "Location[1]",
			"value": "",
			"enabled": true
		},
		{
			"key": "ScreenName[1]",
			"value": "",
			"enabled": true
		},
		{
			"key": "Description[1]",
			"value": "",
			"enabled": true
		},
		{
			"key": "Name[2]",
			"value": "",
			"enabled": true
		},
		{
			"key": "Location[2]",
			"value": "",
			"enabled": true
		},
		{
			"key": "ScreenName[2]",
			"value": "",
			"enabled": true
		},
		{
			"key": "Description[2]",
			"value": "",
			"enabled": true
		},
		{
			"key": "Name[3]",
			"value": "",
			"enabled": true
		},
		{
			"key": "Location[3]",
			"value": "",
			"enabled": true
		},
		{
			"key": "ScreenName[3]",
			"value": "",
			"enabled": true
		},
		{
			"key": "Description[3]",
			"value": "",
			"enabled": true
		},
		{
			"key": "Text",
			"value": "",
			"enabled": true
		},
		{
			"key": "Country[0]",
			"value": "",
			"enabled": true
		},
		{
			"key": "URL[0]",
			"value": "",
			"enabled": true
		},
		{
			"key": "Country[1]",
			"value": "",
			"enabled": true
		},
		{
			"key": "URL[1]",
			"value": "",
			"enabled": true
		},
		{
			"key": "Country[2]",
			"value": "",
			"enabled": true
		},
		{
			"key": "URL[2]",
			"value": "",
			"enabled": true
		},
		{
			"key": "Country[3]",
			"value": "",
			"enabled": true
		},
		{
			"key": "URL[3]",
			"value": "",
			"enabled": true
		},
		{
			"key": "Country[4]",
			"value": "",
			"enabled": true
		},
		{
			"key": "Name[4]",
			"value": "",
			"enabled": true
		},
		{
			"key": "URL[4]",
			"value": "",
			"enabled": true
		},
		{
			"key": "Country[5]",
			"value": "",
			"enabled": true
		},
		{
			"key": "Name[5]",
			"value": "",
			"enabled": true
		},
		{
			"key": "URL[5]",
			"value": "",
			"enabled": true
		},
		{
			"key": "Country[6]",
			"value": "",
			"enabled": true
		},
		{
			"key": "Name[6]",
			"value": "",
			"enabled": true
		},
		{
			"key": "URL[6]",
			"value": "",
			"enabled": true
		},
		{
			"key": "Country[7]",
			"value": "",
			"enabled": true
		},
		{
			"key": "Name[7]",
			"value": "",
			"enabled": true
		},
		{
			"key": "URL[7]",
			"value": "",
			"enabled": true
		},
		{
			"key": "Country[8]",
			"value": "",
			"enabled": true
		},
		{
			"key": "Name[8]",
			"value": "",
			"enabled": true
		},
		{
			"key": "URL[8]",
			"value": "",
			"enabled": true
		},
		{
			"key": "Country[35]",
			"value": "",
			"enabled": true
		},
		{
			"key": "Name[35]",
			"value": "",
			"enabled": true
		},
		{
			"key": "URL[35]",
			"value": "",
			"enabled": true
		},
		{
			"key": "Country[36]",
			"value": "",
			"enabled": true
		},
		{
			"key": "Name[36]",
			"value": "",
			"enabled": true
		},
		{
			"key": "URL[36]",
			"value": "",
			"enabled": true
		},
		{
			"key": "Country[37]",
			"value": "",
			"enabled": true
		},
		{
			"key": "Name[37]",
			"value": "",
			"enabled": true
		},
		{
			"key": "URL[37]",
			"value": "",
			"enabled": true
		},
		{
			"key": "Country[38]",
			"value": "",
			"enabled": true
		},
		{
			"key": "Name[38]",
			"value": "",
			"enabled": true
		},
		{
			"key": "URL[38]",
			"value": "",
			"enabled": true
		},
		{
			"key": "Country[39]",
			"value": "",
			"enabled": true
		},
		{
			"key": "Name[39]",
			"value": "",
			"enabled": true
		},
		{
			"key": "URL[39]",
			"value": "",
			"enabled": true
		},
		{
			"key": "Country[40]",
			"value": "",
			"enabled": true
		},
		{
			"key": "Name[40]",
			"value": "",
			"enabled": true
		},
		{
			"key": "URL[40]",
			"value": "",
			"enabled": true
		},
		{
			"key": "Country[41]",
			"value": "",
			"enabled": true
		},
		{
			"key": "Name[41]",
			"value": "",
			"enabled": true
		},
		{
			"key": "URL[41]",
			"value": "",
			"enabled": true
		},
		{
			"key": "Country[42]",
			"value": "",
			"enabled": true
		},
		{
			"key": "Name[42]",
			"value": "",
			"enabled": true
		},
		{
			"key": "URL[42]",
			"value": "",
			"enabled": true
		},
		{
			"key": "Country[43]",
			"value": "",
			"enabled": true
		},
		{
			"key": "Name[43]",
			"value": "",
			"enabled": true
		},
		{
			"key": "URL[43]",
			"value": "",
			"enabled": true
		},
		{
			"key": "Country[44]",
			"value": "",
			"enabled": true
		},
		{
			"key": "Name[44]",
			"value": "",
			"enabled": true
		},
		{
			"key": "URL[44]",
			"value": "",
			"enabled": true
		},
		{
			"key": "Country[45]",
			"value": "",
			"enabled": true
		},
		{
			"key": "Name[45]",
			"value": "",
			"enabled": true
		},
		{
			"key": "URL[45]",
			"value": "",
			"enabled": true
		},
		{
			"key": "Country[46]",
			"value": "",
			"enabled": true
		},
		{
			"key": "Name[46]",
			"value": "",
			"enabled": true
		},
		{
			"key": "URL[46]",
			"value": "",
			"enabled": true
		},
		{
			"key": "Country[47]",
			"value": "",
			"enabled": true
		},
		{
			"key": "Name[47]",
			"value": "",
			"enabled": true
		},
		{
			"key": "URL[47]",
			"value": "",
			"enabled": true
		},
		{
			"key": "Country[48]",
			"value": "",
			"enabled": true
		},
		{
			"key": "Name[48]",
			"value": "",
			"enabled": true
		},
		{
			"key": "URL[48]",
			"value": "",
			"enabled": true
		},
		{
			"key": "Country[49]",
			"value": "",
			"enabled": true
		},
		{
			"key": "Name[49]",
			"value": "",
			"enabled": true
		},
		{
			"key": "URL[49]",
			"value": "",
			"enabled": true
		},
		{
			"key": "Country[50]",
			"value": "",
			"enabled": true
		},
		{
			"key": "Name[50]",
			"value": "",
			"enabled": true
		},
		{
			"key": "URL[50]",
			"value": "",
			"enabled": true
		},
		{
			"key": "Country[51]",
			"value": "",
			"enabled": true
		},
		{
			"key": "Name[51]",
			"value": "",
			"enabled": true
		},
		{
			"key": "URL[51]",
			"value": "",
			"enabled": true
		},
		{
			"key": "Country[52]",
			"value": "",
			"enabled": true
		},
		{
			"key": "Name[52]",
			"value": "",
			"enabled": true
		},
		{
			"key": "URL[52]",
			"value": "",
			"enabled": true
		},
		{
			"key": "Country[53]",
			"value": "",
			"enabled": true
		},
		{
			"key": "Name[53]",
			"value": "",
			"enabled": true
		},
		{
			"key": "URL[53]",
			"value": "",
			"enabled": true
		},
		{
			"key": "Country[54]",
			"value": "",
			"enabled": true
		},
		{
			"key": "Name[54]",
			"value": "",
			"enabled": true
		},
		{
			"key": "URL[54]",
			"value": "",
			"enabled": true
		},
		{
			"key": "Country[55]",
			"value": "",
			"enabled": true
		},
		{
			"key": "Name[55]",
			"value": "",
			"enabled": true
		},
		{
			"key": "URL[55]",
			"value": "",
			"enabled": true
		},
		{
			"key": "Country[56]",
			"value": "",
			"enabled": true
		},
		{
			"key": "Name[56]",
			"value": "",
			"enabled": true
		},
		{
			"key": "URL[56]",
			"value": "",
			"enabled": true
		},
		{
			"key": "Country[57]",
			"value": "",
			"enabled": true
		},
		{
			"key": "Name[57]",
			"value": "",
			"enabled": true
		},
		{
			"key": "URL[57]",
			"value": "",
			"enabled": true
		},
		{
			"key": "Country[58]",
			"value": "",
			"enabled": true
		},
		{
			"key": "Name[58]",
			"value": "",
			"enabled": true
		},
		{
			"key": "URL[58]",
			"value": "",
			"enabled": true
		},
		{
			"key": "Country[59]",
			"value": "",
			"enabled": true
		},
		{
			"key": "Name[59]",
			"value": "",
			"enabled": true
		},
		{
			"key": "URL[59]",
			"value": "",
			"enabled": true
		},
		{
			"key": "Country[60]",
			"value": "",
			"enabled": true
		},
		{
			"key": "Name[60]",
			"value": "",
			"enabled": true
		},
		{
			"key": "URL[60]",
			"value": "",
			"enabled": true
		},
		{
			"key": "Country[61]",
			"value": "",
			"enabled": true
		},
		{
			"key": "Name[61]",
			"value": "",
			"enabled": true
		},
		{
			"key": "URL[61]",
			"value": "",
			"enabled": true
		},
		{
			"key": "Country[62]",
			"value": "",
			"enabled": true
		},
		{
			"key": "Name[62]",
			"value": "",
			"enabled": true
		},
		{
			"key": "URL[62]",
			"value": "",
			"enabled": true
		},
		{
			"key": "Country[63]",
			"value": "",
			"enabled": true
		},
		{
			"key": "Name[63]",
			"value": "",
			"enabled": true
		},
		{
			"key": "URL[63]",
			"value": "",
			"enabled": true
		},
		{
			"key": "Country[64]",
			"value": "",
			"enabled": true
		},
		{
			"key": "Name[64]",
			"value": "",
			"enabled": true
		},
		{
			"key": "URL[64]",
			"value": "",
			"enabled": true
		},
		{
			"key": "Country[65]",
			"value": "",
			"enabled": true
		},
		{
			"key": "Name[65]",
			"value": "",
			"enabled": true
		},
		{
			"key": "URL[65]",
			"value": "",
			"enabled": true
		},
		{
			"key": "Country[66]",
			"value": "",
			"enabled": true
		},
		{
			"key": "Name[66]",
			"value": "",
			"enabled": true
		},
		{
			"key": "URL[66]",
			"value": "",
			"enabled": true
		},
		{
			"key": "Country[67]",
			"value": "",
			"enabled": true
		},
		{
			"key": "Name[67]",
			"value": "",
			"enabled": true
		},
		{
			"key": "URL[67]",
			"value": "",
			"enabled": true
		},
		{
			"key": "Country[68]",
			"value": "",
			"enabled": true
		},
		{
			"key": "Name[68]",
			"value": "",
			"enabled": true
		},
		{
			"key": "URL[68]",
			"value": "",
			"enabled": true
		},
		{
			"key": "Country[69]",
			"value": "",
			"enabled": true
		},
		{
			"key": "Name[69]",
			"value": "",
			"enabled": true
		},
		{
			"key": "URL[69]",
			"value": "",
			"enabled": true
		},
		{
			"key": "Country[70]",
			"value": "",
			"enabled": true
		},
		{
			"key": "Name[70]",
			"value": "",
			"enabled": true
		},
		{
			"key": "URL[70]",
			"value": "",
			"enabled": true
		},
		{
			"key": "Country[71]",
			"value": "",
			"enabled": true
		},
		{
			"key": "Name[71]",
			"value": "",
			"enabled": true
		},
		{
			"key": "URL[71]",
			"value": "",
			"enabled": true
		},
		{
			"key": "Country[72]",
			"value": "",
			"enabled": true
		},
		{
			"key": "Name[72]",
			"value": "",
			"enabled": true
		},
		{
			"key": "URL[72]",
			"value": "",
			"enabled": true
		},
		{
			"key": "Country[73]",
			"value": "",
			"enabled": true
		},
		{
			"key": "Name[73]",
			"value": "",
			"enabled": true
		},
		{
			"key": "URL[73]",
			"value": "",
			"enabled": true
		},
		{
			"key": "Country[74]",
			"value": "",
			"enabled": true
		},
		{
			"key": "Name[74]",
			"value": "",
			"enabled": true
		},
		{
			"key": "URL[74]",
			"value": "",
			"enabled": true
		},
		{
			"key": "Country[75]",
			"value": "",
			"enabled": true
		},
		{
			"key": "Name[75]",
			"value": "",
			"enabled": true
		},
		{
			"key": "URL[75]",
			"value": "",
			"enabled": true
		},
		{
			"key": "Country[76]",
			"value": "",
			"enabled": true
		},
		{
			"key": "Name[76]",
			"value": "",
			"enabled": true
		},
		{
			"key": "URL[76]",
			"value": "",
			"enabled": true
		},
		{
			"key": "Country[77]",
			"value": "",
			"enabled": true
		},
		{
			"key": "Name[77]",
			"value": "",
			"enabled": true
		},
		{
			"key": "URL[77]",
			"value": "",
			"enabled": true
		},
		{
			"key": "Country[78]",
			"value": "",
			"enabled": true
		},
		{
			"key": "Name[78]",
			"value": "",
			"enabled": true
		},
		{
			"key": "URL[78]",
			"value": "",
			"enabled": true
		},
		{
			"key": "Country[79]",
			"value": "",
			"enabled": true
		},
		{
			"key": "Name[79]",
			"value": "",
			"enabled": true
		},
		{
			"key": "URL[79]",
			"value": "",
			"enabled": true
		},
		{
			"key": "Country[80]",
			"value": "",
			"enabled": true
		},
		{
			"key": "Name[80]",
			"value": "",
			"enabled": true
		},
		{
			"key": "URL[80]",
			"value": "",
			"enabled": true
		},
		{
			"key": "Country[81]",
			"value": "",
			"enabled": true
		},
		{
			"key": "Name[81]",
			"value": "",
			"enabled": true
		},
		{
			"key": "URL[81]",
			"value": "",
			"enabled": true
		},
		{
			"key": "Country[82]",
			"value": "",
			"enabled": true
		},
		{
			"key": "Name[82]",
			"value": "",
			"enabled": true
		},
		{
			"key": "URL[82]",
			"value": "",
			"enabled": true
		},
		{
			"key": "Country[83]",
			"value": "",
			"enabled": true
		},
		{
			"key": "Name[83]",
			"value": "",
			"enabled": true
		},
		{
			"key": "URL[83]",
			"value": "",
			"enabled": true
		},
		{
			"key": "Country[84]",
			"value": "",
			"enabled": true
		},
		{
			"key": "Name[84]",
			"value": "",
			"enabled": true
		},
		{
			"key": "URL[84]",
			"value": "",
			"enabled": true
		},
		{
			"key": "Country[85]",
			"value": "",
			"enabled": true
		},
		{
			"key": "Name[85]",
			"value": "",
			"enabled": true
		},
		{
			"key": "URL[85]",
			"value": "",
			"enabled": true
		},
		{
			"key": "Country[86]",
			"value": "",
			"enabled": true
		},
		{
			"key": "Name[86]",
			"value": "",
			"enabled": true
		},
		{
			"key": "URL[86]",
			"value": "",
			"enabled": true
		},
		{
			"key": "Country[87]",
			"value": "",
			"enabled": true
		},
		{
			"key": "Name[87]",
			"value": "",
			"enabled": true
		},
		{
			"key": "URL[87]",
			"value": "",
			"enabled": true
		},
		{
			"key": "Country[88]",
			"value": "",
			"enabled": true
		},
		{
			"key": "Name[88]",
			"value": "",
			"enabled": true
		},
		{
			"key": "URL[88]",
			"value": "",
			"enabled": true
		},
		{
			"key": "Country[89]",
			"value": "",
			"enabled": true
		},
		{
			"key": "Name[89]",
			"value": "",
			"enabled": true
		},
		{
			"key": "URL[89]",
			"value": "",
			"enabled": true
		},
		{
			"key": "Country[90]",
			"value": "",
			"enabled": true
		},
		{
			"key": "Name[90]",
			"value": "",
			"enabled": true
		},
		{
			"key": "URL[90]",
			"value": "",
			"enabled": true
		},
		{
			"key": "Country[91]",
			"value": "",
			"enabled": true
		},
		{
			"key": "Name[91]",
			"value": "",
			"enabled": true
		},
		{
			"key": "URL[91]",
			"value": "",
			"enabled": true
		},
		{
			"key": "Country[92]",
			"value": "",
			"enabled": true
		},
		{
			"key": "Name[92]",
			"value": "",
			"enabled": true
		},
		{
			"key": "URL[92]",
			"value": "",
			"enabled": true
		},
		{
			"key": "Country[93]",
			"value": "",
			"enabled": true
		},
		{
			"key": "Name[93]",
			"value": "",
			"enabled": true
		},
		{
			"key": "URL[93]",
			"value": "",
			"enabled": true
		},
		{
			"key": "Country[94]",
			"value": "",
			"enabled": true
		},
		{
			"key": "Name[94]",
			"value": "",
			"enabled": true
		},
		{
			"key": "URL[94]",
			"value": "",
			"enabled": true
		},
		{
			"key": "Country[95]",
			"value": "",
			"enabled": true
		},
		{
			"key": "Name[95]",
			"value": "",
			"enabled": true
		},
		{
			"key": "URL[95]",
			"value": "",
			"enabled": true
		},
		{
			"key": "Country[96]",
			"value": "",
			"enabled": true
		},
		{
			"key": "Name[96]",
			"value": "",
			"enabled": true
		},
		{
			"key": "URL[96]",
			"value": "",
			"enabled": true
		},
		{
			"key": "Country[97]",
			"value": "",
			"enabled": true
		},
		{
			"key": "Name[97]",
			"value": "",
			"enabled": true
		},
		{
			"key": "URL[97]",
			"value": "",
			"enabled": true
		},
		{
			"key": "Country[98]",
			"value": "",
			"enabled": true
		},
		{
			"key": "Name[98]",
			"value": "",
			"enabled": true
		},
		{
			"key": "URL[98]",
			"value": "",
			"enabled": true
		},
		{
			"key": "Country[99]",
			"value": "",
			"enabled": true
		},
		{
			"key": "Name[99]",
			"value": "",
			"enabled": true
		},
		{
			"key": "URL[99]",
			"value": "",
			"enabled": true
		},
		{
			"key": "Country[100]",
			"value": "",
			"enabled": true
		},
		{
			"key": "Name[100]",
			"value": "",
			"enabled": true
		},
		{
			"key": "URL[100]",
			"value": "",
			"enabled": true
		},
		{
			"key": "Country[101]",
			"value": "",
			"enabled": true
		},
		{
			"key": "Name[101]",
			"value": "",
			"enabled": true
		},
		{
			"key": "URL[101]",
			"value": "",
			"enabled": true
		},
		{
			"key": "Country[102]",
			"value": "",
			"enabled": true
		},
		{
			"key": "Name[102]",
			"value": "",
			"enabled": true
		},
		{
			"key": "URL[102]",
			"value": "",
			"enabled": true
		},
		{
			"key": "Country[103]",
			"value": "",
			"enabled": true
		},
		{
			"key": "Name[103]",
			"value": "",
			"enabled": true
		},
		{
			"key": "URL[103]",
			"value": "",
			"enabled": true
		},
		{
			"key": "Country[104]",
			"value": "",
			"enabled": true
		},
		{
			"key": "Name[104]",
			"value": "",
			"enabled": true
		},
		{
			"key": "URL[104]",
			"value": "",
			"enabled": true
		},
		{
			"key": "Country[105]",
			"value": "",
			"enabled": true
		},
		{
			"key": "Name[105]",
			"value": "",
			"enabled": true
		},
		{
			"key": "URL[105]",
			"value": "",
			"enabled": true
		},
		{
			"key": "Country[106]",
			"value": "",
			"enabled": true
		},
		{
			"key": "Name[106]",
			"value": "",
			"enabled": true
		},
		{
			"key": "URL[106]",
			"value": "",
			"enabled": true
		},
		{
			"key": "Country[107]",
			"value": "",
			"enabled": true
		},
		{
			"key": "Name[107]",
			"value": "",
			"enabled": true
		},
		{
			"key": "URL[107]",
			"value": "",
			"enabled": true
		},
		{
			"key": "Country[108]",
			"value": "",
			"enabled": true
		},
		{
			"key": "Name[108]",
			"value": "",
			"enabled": true
		},
		{
			"key": "URL[108]",
			"value": "",
			"enabled": true
		},
		{
			"key": "Country[109]",
			"value": "",
			"enabled": true
		},
		{
			"key": "Name[109]",
			"value": "",
			"enabled": true
		},
		{
			"key": "URL[109]",
			"value": "",
			"enabled": true
		},
		{
			"key": "Country[110]",
			"value": "",
			"enabled": true
		},
		{
			"key": "Name[110]",
			"value": "",
			"enabled": true
		},
		{
			"key": "URL[110]",
			"value": "",
			"enabled": true
		},
		{
			"key": "Country[111]",
			"value": "",
			"enabled": true
		},
		{
			"key": "Name[111]",
			"value": "",
			"enabled": true
		},
		{
			"key": "URL[111]",
			"value": "",
			"enabled": true
		},
		{
			"key": "Country[112]",
			"value": "",
			"enabled": true
		},
		{
			"key": "Name[112]",
			"value": "",
			"enabled": true
		},
		{
			"key": "URL[112]",
			"value": "",
			"enabled": true
		},
		{
			"key": "Country[113]",
			"value": "",
			"enabled": true
		},
		{
			"key": "Name[113]",
			"value": "",
			"enabled": true
		},
		{
			"key": "URL[113]",
			"value": "",
			"enabled": true
		},
		{
			"key": "Country[114]",
			"value": "",
			"enabled": true
		},
		{
			"key": "Name[114]",
			"value": "",
			"enabled": true
		},
		{
			"key": "URL[114]",
			"value": "",
			"enabled": true
		},
		{
			"key": "Country[115]",
			"value": "",
			"enabled": true
		},
		{
			"key": "Name[115]",
			"value": "",
			"enabled": true
		},
		{
			"key": "URL[115]",
			"value": "",
			"enabled": true
		},
		{
			"key": "Country[116]",
			"value": "",
			"enabled": true
		},
		{
			"key": "Name[116]",
			"value": "",
			"enabled": true
		},
		{
			"key": "URL[116]",
			"value": "",
			"enabled": true
		},
		{
			"key": "Country[117]",
			"value": "",
			"enabled": true
		},
		{
			"key": "Name[117]",
			"value": "",
			"enabled": true
		},
		{
			"key": "URL[117]",
			"value": "",
			"enabled": true
		},
		{
			"key": "Country[118]",
			"value": "",
			"enabled": true
		},
		{
			"key": "Name[118]",
			"value": "",
			"enabled": true
		},
		{
			"key": "URL[118]",
			"value": "",
			"enabled": true
		},
		{
			"key": "Country[119]",
			"value": "",
			"enabled": true
		},
		{
			"key": "Name[119]",
			"value": "",
			"enabled": true
		},
		{
			"key": "URL[119]",
			"value": "",
			"enabled": true
		},
		{
			"key": "Country[120]",
			"value": "",
			"enabled": true
		},
		{
			"key": "Name[120]",
			"value": "",
			"enabled": true
		},
		{
			"key": "URL[120]",
			"value": "",
			"enabled": true
		},
		{
			"key": "Country[121]",
			"value": "",
			"enabled": true
		},
		{
			"key": "Name[121]",
			"value": "",
			"enabled": true
		},
		{
			"key": "URL[121]",
			"value": "",
			"enabled": true
		},
		{
			"key": "Country[122]",
			"value": "",
			"enabled": true
		},
		{
			"key": "Name[122]",
			"value": "",
			"enabled": true
		},
		{
			"key": "URL[122]",
			"value": "",
			"enabled": true
		},
		{
			"key": "Country[123]",
			"value": "",
			"enabled": true
		},
		{
			"key": "Name[123]",
			"value": "",
			"enabled": true
		},
		{
			"key": "URL[123]",
			"value": "",
			"enabled": true
		},
		{
			"key": "Country[124]",
			"value": "",
			"enabled": true
		},
		{
			"key": "Name[124]",
			"value": "",
			"enabled": true
		},
		{
			"key": "URL[124]",
			"value": "",
			"enabled": true
		},
		{
			"key": "Country[125]",
			"value": "",
			"enabled": true
		},
		{
			"key": "Name[125]",
			"value": "",
			"enabled": true
		},
		{
			"key": "URL[125]",
			"value": "",
			"enabled": true
		},
		{
			"key": "Country[126]",
			"value": "",
			"enabled": true
		},
		{
			"key": "Name[126]",
			"value": "",
			"enabled": true
		},
		{
			"key": "URL[126]",
			"value": "",
			"enabled": true
		},
		{
			"key": "Country[127]",
			"value": "",
			"enabled": true
		},
		{
			"key": "Name[127]",
			"value": "",
			"enabled": true
		},
		{
			"key": "URL[127]",
			"value": "",
			"enabled": true
		},
		{
			"key": "Country[128]",
			"value": "",
			"enabled": true
		},
		{
			"key": "Name[128]",
			"value": "",
			"enabled": true
		},
		{
			"key": "URL[128]",
			"value": "",
			"enabled": true
		},
		{
			"key": "Country[129]",
			"value": "",
			"enabled": true
		},
		{
			"key": "Name[129]",
			"value": "",
			"enabled": true
		},
		{
			"key": "URL[129]",
			"value": "",
			"enabled": true
		},
		{
			"key": "Country[130]",
			"value": "",
			"enabled": true
		},
		{
			"key": "Name[130]",
			"value": "",
			"enabled": true
		},
		{
			"key": "URL[130]",
			"value": "",
			"enabled": true
		},
		{
			"key": "Country[131]",
			"value": "",
			"enabled": true
		},
		{
			"key": "Name[131]",
			"value": "",
			"enabled": true
		},
		{
			"key": "URL[131]",
			"value": "",
			"enabled": true
		},
		{
			"key": "Country[132]",
			"value": "",
			"enabled": true
		},
		{
			"key": "Name[132]",
			"value": "",
			"enabled": true
		},
		{
			"key": "URL[132]",
			"value": "",
			"enabled": true
		},
		{
			"key": "Country[133]",
			"value": "",
			"enabled": true
		},
		{
			"key": "Name[133]",
			"value": "",
			"enabled": true
		},
		{
			"key": "URL[133]",
			"value": "",
			"enabled": true
		},
		{
			"key": "Country[134]",
			"value": "",
			"enabled": true
		},
		{
			"key": "Name[134]",
			"value": "",
			"enabled": true
		},
		{
			"key": "URL[134]",
			"value": "",
			"enabled": true
		},
		{
			"key": "Country[135]",
			"value": "",
			"enabled": true
		},
		{
			"key": "Name[135]",
			"value": "",
			"enabled": true
		},
		{
			"key": "URL[135]",
			"value": "",
			"enabled": true
		},
		{
			"key": "Country[136]",
			"value": "",
			"enabled": true
		},
		{
			"key": "Name[136]",
			"value": "",
			"enabled": true
		},
		{
			"key": "URL[136]",
			"value": "",
			"enabled": true
		},
		{
			"key": "Country[137]",
			"value": "",
			"enabled": true
		},
		{
			"key": "Name[137]",
			"value": "",
			"enabled": true
		},
		{
			"key": "URL[137]",
			"value": "",
			"enabled": true
		},
		{
			"key": "Country[138]",
			"value": "",
			"enabled": true
		},
		{
			"key": "Name[138]",
			"value": "",
			"enabled": true
		},
		{
			"key": "URL[138]",
			"value": "",
			"enabled": true
		},
		{
			"key": "Country[139]",
			"value": "",
			"enabled": true
		},
		{
			"key": "Name[139]",
			"value": "",
			"enabled": true
		},
		{
			"key": "URL[139]",
			"value": "",
			"enabled": true
		},
		{
			"key": "Country[140]",
			"value": "",
			"enabled": true
		},
		{
			"key": "Name[140]",
			"value": "",
			"enabled": true
		},
		{
			"key": "URL[140]",
			"value": "",
			"enabled": true
		},
		{
			"key": "Country[141]",
			"value": "",
			"enabled": true
		},
		{
			"key": "Name[141]",
			"value": "",
			"enabled": true
		},
		{
			"key": "URL[141]",
			"value": "",
			"enabled": true
		},
		{
			"key": "Country[142]",
			"value": "",
			"enabled": true
		},
		{
			"key": "Name[142]",
			"value": "",
			"enabled": true
		},
		{
			"key": "URL[142]",
			"value": "",
			"enabled": true
		},
		{
			"key": "Country[143]",
			"value": "",
			"enabled": true
		},
		{
			"key": "Name[143]",
			"value": "",
			"enabled": true
		},
		{
			"key": "URL[143]",
			"value": "",
			"enabled": true
		},
		{
			"key": "Country[144]",
			"value": "",
			"enabled": true
		},
		{
			"key": "Name[144]",
			"value": "",
			"enabled": true
		},
		{
			"key": "URL[144]",
			"value": "",
			"enabled": true
		},
		{
			"key": "Country[145]",
			"value": "",
			"enabled": true
		},
		{
			"key": "Name[145]",
			"value": "",
			"enabled": true
		},
		{
			"key": "URL[145]",
			"value": "",
			"enabled": true
		},
		{
			"key": "Country[146]",
			"value": "",
			"enabled": true
		},
		{
			"key": "Name[146]",
			"value": "",
			"enabled": true
		},
		{
			"key": "URL[146]",
			"value": "",
			"enabled": true
		},
		{
			"key": "Country[147]",
			"value": "",
			"enabled": true
		},
		{
			"key": "Name[147]",
			"value": "",
			"enabled": true
		},
		{
			"key": "URL[147]",
			"value": "",
			"enabled": true
		},
		{
			"key": "Country[148]",
			"value": "",
			"enabled": true
		},
		{
			"key": "Name[148]",
			"value": "",
			"enabled": true
		},
		{
			"key": "URL[148]",
			"value": "",
			"enabled": true
		},
		{
			"key": "Country[149]",
			"value": "",
			"enabled": true
		},
		{
			"key": "Name[149]",
			"value": "",
			"enabled": true
		},
		{
			"key": "URL[149]",
			"value": "",
			"enabled": true
		},
		{
			"key": "Country[150]",
			"value": "",
			"enabled": true
		},
		{
			"key": "Name[150]",
			"value": "",
			"enabled": true
		},
		{
			"key": "URL[150]",
			"value": "",
			"enabled": true
		},
		{
			"key": "Country[151]",
			"value": "",
			"enabled": true
		},
		{
			"key": "Name[151]",
			"value": "",
			"enabled": true
		},
		{
			"key": "URL[151]",
			"value": "",
			"enabled": true
		},
		{
			"key": "Country[152]",
			"value": "",
			"enabled": true
		},
		{
			"key": "Name[152]",
			"value": "",
			"enabled": true
		},
		{
			"key": "URL[152]",
			"value": "",
			"enabled": true
		},
		{
			"key": "Country[153]",
			"value": "",
			"enabled": true
		},
		{
			"key": "Name[153]",
			"value": "",
			"enabled": true
		},
		{
			"key": "URL[153]",
			"value": "",
			"enabled": true
		},
		{
			"key": "Country[154]",
			"value": "",
			"enabled": true
		},
		{
			"key": "Name[154]",
			"value": "",
			"enabled": true
		},
		{
			"key": "URL[154]",
			"value": "",
			"enabled": true
		},
		{
			"key": "Country[155]",
			"value": "",
			"enabled": true
		},
		{
			"key": "Name[155]",
			"value": "",
			"enabled": true
		},
		{
			"key": "URL[155]",
			"value": "",
			"enabled": true
		},
		{
			"key": "Country[156]",
			"value": "",
			"enabled": true
		},
		{
			"key": "Name[156]",
			"value": "",
			"enabled": true
		},
		{
			"key": "URL[156]",
			"value": "",
			"enabled": true
		},
		{
			"key": "Country[157]",
			"value": "",
			"enabled": true
		},
		{
			"key": "Name[157]",
			"value": "",
			"enabled": true
		},
		{
			"key": "URL[157]",
			"value": "",
			"enabled": true
		},
		{
			"key": "Country[158]",
			"value": "",
			"enabled": true
		},
		{
			"key": "Name[158]",
			"value": "",
			"enabled": true
		},
		{
			"key": "URL[158]",
			"value": "",
			"enabled": true
		},
		{
			"key": "Country[159]",
			"value": "",
			"enabled": true
		},
		{
			"key": "Name[159]",
			"value": "",
			"enabled": true
		},
		{
			"key": "URL[159]",
			"value": "",
			"enabled": true
		},
		{
			"key": "Country[160]",
			"value": "",
			"enabled": true
		},
		{
			"key": "Name[160]",
			"value": "",
			"enabled": true
		},
		{
			"key": "URL[160]",
			"value": "",
			"enabled": true
		},
		{
			"key": "Country[161]",
			"value": "",
			"enabled": true
		},
		{
			"key": "Name[161]",
			"value": "",
			"enabled": true
		},
		{
			"key": "URL[161]",
			"value": "",
			"enabled": true
		},
		{
			"key": "Country[162]",
			"value": "",
			"enabled": true
		},
		{
			"key": "Name[162]",
			"value": "",
			"enabled": true
		},
		{
			"key": "URL[162]",
			"value": "",
			"enabled": true
		},
		{
			"key": "Country[163]",
			"value": "",
			"enabled": true
		},
		{
			"key": "Name[163]",
			"value": "",
			"enabled": true
		},
		{
			"key": "URL[163]",
			"value": "",
			"enabled": true
		},
		{
			"key": "Country[164]",
			"value": "",
			"enabled": true
		},
		{
			"key": "Name[164]",
			"value": "",
			"enabled": true
		},
		{
			"key": "URL[164]",
			"value": "",
			"enabled": true
		},
		{
			"key": "Country[165]",
			"value": "",
			"enabled": true
		},
		{
			"key": "Name[165]",
			"value": "",
			"enabled": true
		},
		{
			"key": "URL[165]",
			"value": "",
			"enabled": true
		},
		{
			"key": "Country[166]",
			"value": "",
			"enabled": true
		},
		{
			"key": "Name[166]",
			"value": "",
			"enabled": true
		},
		{
			"key": "URL[166]",
			"value": "",
			"enabled": true
		},
		{
			"key": "Country[167]",
			"value": "",
			"enabled": true
		},
		{
			"key": "Name[167]",
			"value": "",
			"enabled": true
		},
		{
			"key": "URL[167]",
			"value": "",
			"enabled": true
		},
		{
			"key": "Country[168]",
			"value": "",
			"enabled": true
		},
		{
			"key": "Name[168]",
			"value": "",
			"enabled": true
		},
		{
			"key": "URL[168]",
			"value": "",
			"enabled": true
		},
		{
			"key": "Country[169]",
			"value": "",
			"enabled": true
		},
		{
			"key": "Name[169]",
			"value": "",
			"enabled": true
		},
		{
			"key": "URL[169]",
			"value": "",
			"enabled": true
		},
		{
			"key": "Country[170]",
			"value": "",
			"enabled": true
		},
		{
			"key": "Name[170]",
			"value": "",
			"enabled": true
		},
		{
			"key": "URL[170]",
			"value": "",
			"enabled": true
		},
		{
			"key": "Country[171]",
			"value": "",
			"enabled": true
		},
		{
			"key": "Name[171]",
			"value": "",
			"enabled": true
		},
		{
			"key": "URL[171]",
			"value": "",
			"enabled": true
		},
		{
			"key": "Country[172]",
			"value": "",
			"enabled": true
		},
		{
			"key": "Name[172]",
			"value": "",
			"enabled": true
		},
		{
			"key": "URL[172]",
			"value": "",
			"enabled": true
		},
		{
			"key": "Country[173]",
			"value": "",
			"enabled": true
		},
		{
			"key": "Name[173]",
			"value": "",
			"enabled": true
		},
		{
			"key": "URL[173]",
			"value": "",
			"enabled": true
		},
		{
			"key": "Country[174]",
			"value": "",
			"enabled": true
		},
		{
			"key": "Name[174]",
			"value": "",
			"enabled": true
		},
		{
			"key": "URL[174]",
			"value": "",
			"enabled": true
		},
		{
			"key": "Country[175]",
			"value": "",
			"enabled": true
		},
		{
			"key": "Name[175]",
			"value": "",
			"enabled": true
		},
		{
			"key": "URL[175]",
			"value": "",
			"enabled": true
		},
		{
			"key": "Country[176]",
			"value": "",
			"enabled": true
		},
		{
			"key": "Name[176]",
			"value": "",
			"enabled": true
		},
		{
			"key": "URL[176]",
			"value": "",
			"enabled": true
		},
		{
			"key": "Country[177]",
			"value": "",
			"enabled": true
		},
		{
			"key": "Name[177]",
			"value": "",
			"enabled": true
		},
		{
			"key": "URL[177]",
			"value": "",
			"enabled": true
		},
		{
			"key": "Country[178]",
			"value": "",
			"enabled": true
		},
		{
			"key": "Name[178]",
			"value": "",
			"enabled": true
		},
		{
			"key": "URL[178]",
			"value": "",
			"enabled": true
		},
		{
			"key": "Country[179]",
			"value": "",
			"enabled": true
		},
		{
			"key": "Name[179]",
			"value": "",
			"enabled": true
		},
		{
			"key": "URL[179]",
			"value": "",
			"enabled": true
		},
		{
			"key": "Country[180]",
			"value": "",
			"enabled": true
		},
		{
			"key": "Name[180]",
			"value": "",
			"enabled": true
		},
		{
			"key": "URL[180]",
			"value": "",
			"enabled": true
		},
		{
			"key": "Country[181]",
			"value": "",
			"enabled": true
		},
		{
			"key": "Name[181]",
			"value": "",
			"enabled": true
		},
		{
			"key": "URL[181]",
			"value": "",
			"enabled": true
		},
		{
			"key": "Country[182]",
			"value": "",
			"enabled": true
		},
		{
			"key": "Name[182]",
			"value": "",
			"enabled": true
		},
		{
			"key": "URL[182]",
			"value": "",
			"enabled": true
		},
		{
			"key": "Country[183]",
			"value": "",
			"enabled": true
		},
		{
			"key": "Name[183]",
			"value": "",
			"enabled": true
		},
		{
			"key": "URL[183]",
			"value": "",
			"enabled": true
		},
		{
			"key": "Country[184]",
			"value": "",
			"enabled": true
		},
		{
			"key": "Name[184]",
			"value": "",
			"enabled": true
		},
		{
			"key": "URL[184]",
			"value": "",
			"enabled": true
		},
		{
			"key": "Country[185]",
			"value": "",
			"enabled": true
		},
		{
			"key": "Name[185]",
			"value": "",
			"enabled": true
		},
		{
			"key": "URL[185]",
			"value": "",
			"enabled": true
		},
		{
			"key": "Country[186]",
			"value": "",
			"enabled": true
		},
		{
			"key": "Name[186]",
			"value": "",
			"enabled": true
		},
		{
			"key": "URL[186]",
			"value": "",
			"enabled": true
		},
		{
			"key": "Country[187]",
			"value": "",
			"enabled": true
		},
		{
			"key": "Name[187]",
			"value": "",
			"enabled": true
		},
		{
			"key": "URL[187]",
			"value": "",
			"enabled": true
		},
		{
			"key": "Country[188]",
			"value": "",
			"enabled": true
		},
		{
			"key": "Name[188]",
			"value": "",
			"enabled": true
		},
		{
			"key": "URL[188]",
			"value": "",
			"enabled": true
		},
		{
			"key": "Country[189]",
			"value": "",
			"enabled": true
		},
		{
			"key": "Name[189]",
			"value": "",
			"enabled": true
		},
		{
			"key": "URL[189]",
			"value": "",
			"enabled": true
		},
		{
			"key": "Country[190]",
			"value": "",
			"enabled": true
		},
		{
			"key": "Name[190]",
			"value": "",
			"enabled": true
		},
		{
			"key": "URL[190]",
			"value": "",
			"enabled": true
		},
		{
			"key": "Country[191]",
			"value": "",
			"enabled": true
		},
		{
			"key": "Name[191]",
			"value": "",
			"enabled": true
		},
		{
			"key": "URL[191]",
			"value": "",
			"enabled": true
		},
		{
			"key": "Country[192]",
			"value": "",
			"enabled": true
		},
		{
			"key": "Name[192]",
			"value": "",
			"enabled": true
		},
		{
			"key": "URL[192]",
			"value": "",
			"enabled": true
		},
		{
			"key": "Country[193]",
			"value": "",
			"enabled": true
		},
		{
			"key": "Name[193]",
			"value": "",
			"enabled": true
		},
		{
			"key": "URL[193]",
			"value": "",
			"enabled": true
		},
		{
			"key": "Country[194]",
			"value": "",
			"enabled": true
		},
		{
			"key": "Name[194]",
			"value": "",
			"enabled": true
		},
		{
			"key": "URL[194]",
			"value": "",
			"enabled": true
		},
		{
			"key": "Country[195]",
			"value": "",
			"enabled": true
		},
		{
			"key": "Name[195]",
			"value": "",
			"enabled": true
		},
		{
			"key": "URL[195]",
			"value": "",
			"enabled": true
		},
		{
			"key": "Country[196]",
			"value": "",
			"enabled": true
		},
		{
			"key": "Name[196]",
			"value": "",
			"enabled": true
		},
		{
			"key": "URL[196]",
			"value": "",
			"enabled": true
		},
		{
			"key": "Country[197]",
			"value": "",
			"enabled": true
		},
		{
			"key": "Name[197]",
			"value": "",
			"enabled": true
		},
		{
			"key": "URL[197]",
			"value": "",
			"enabled": true
		},
		{
			"key": "Country[198]",
			"value": "",
			"enabled": true
		},
		{
			"key": "Name[198]",
			"value": "",
			"enabled": true
		},
		{
			"key": "URL[198]",
			"value": "",
			"enabled": true
		},
		{
			"key": "Country[199]",
			"value": "",
			"enabled": true
		},
		{
			"key": "Name[199]",
			"value": "",
			"enabled": true
		},
		{
			"key": "URL[199]",
			"value": "",
			"enabled": true
		},
		{
			"key": "Country[200]",
			"value": "",
			"enabled": true
		},
		{
			"key": "Name[200]",
			"value": "",
			"enabled": true
		},
		{
			"key": "URL[200]",
			"value": "",
			"enabled": true
		},
		{
			"key": "Country[201]",
			"value": "",
			"enabled": true
		},
		{
			"key": "Name[201]",
			"value": "",
			"enabled": true
		},
		{
			"key": "URL[201]",
			"value": "",
			"enabled": true
		},
		{
			"key": "Country[202]",
			"value": "",
			"enabled": true
		},
		{
			"key": "Name[202]",
			"value": "",
			"enabled": true
		},
		{
			"key": "URL[202]",
			"value": "",
			"enabled": true
		},
		{
			"key": "Country[203]",
			"value": "",
			"enabled": true
		},
		{
			"key": "Name[203]",
			"value": "",
			"enabled": true
		},
		{
			"key": "URL[203]",
			"value": "",
			"enabled": true
		},
		{
			"key": "Country[204]",
			"value": "",
			"enabled": true
		},
		{
			"key": "Name[204]",
			"value": "",
			"enabled": true
		},
		{
			"key": "URL[204]",
			"value": "",
			"enabled": true
		},
		{
			"key": "Country[205]",
			"value": "",
			"enabled": true
		},
		{
			"key": "Name[205]",
			"value": "",
			"enabled": true
		},
		{
			"key": "URL[205]",
			"value": "",
			"enabled": true
		},
		{
			"key": "Country[206]",
			"value": "",
			"enabled": true
		},
		{
			"key": "Name[206]",
			"value": "",
			"enabled": true
		},
		{
			"key": "URL[206]",
			"value": "",
			"enabled": true
		},
		{
			"key": "Country[207]",
			"value": "",
			"enabled": true
		},
		{
			"key": "Name[207]",
			"value": "",
			"enabled": true
		},
		{
			"key": "URL[207]",
			"value": "",
			"enabled": true
		},
		{
			"key": "Country[208]",
			"value": "",
			"enabled": true
		},
		{
			"key": "Name[208]",
			"value": "",
			"enabled": true
		},
		{
			"key": "URL[208]",
			"value": "",
			"enabled": true
		},
		{
			"key": "Country[209]",
			"value": "",
			"enabled": true
		},
		{
			"key": "Name[209]",
			"value": "",
			"enabled": true
		},
		{
			"key": "URL[209]",
			"value": "",
			"enabled": true
		},
		{
			"key": "Country[210]",
			"value": "",
			"enabled": true
		},
		{
			"key": "Name[210]",
			"value": "",
			"enabled": true
		},
		{
			"key": "URL[210]",
			"value": "",
			"enabled": true
		},
		{
			"key": "Country[211]",
			"value": "",
			"enabled": true
		},
		{
			"key": "Name[211]",
			"value": "",
			"enabled": true
		},
		{
			"key": "URL[211]",
			"value": "",
			"enabled": true
		},
		{
			"key": "Country[212]",
			"value": "",
			"enabled": true
		},
		{
			"key": "Name[212]",
			"value": "",
			"enabled": true
		},
		{
			"key": "URL[212]",
			"value": "",
			"enabled": true
		},
		{
			"key": "Country[213]",
			"value": "",
			"enabled": true
		},
		{
			"key": "Name[213]",
			"value": "",
			"enabled": true
		},
		{
			"key": "URL[213]",
			"value": "",
			"enabled": true
		},
		{
			"key": "Country[214]",
			"value": "",
			"enabled": true
		},
		{
			"key": "Name[214]",
			"value": "",
			"enabled": true
		},
		{
			"key": "URL[214]",
			"value": "",
			"enabled": true
		},
		{
			"key": "Country[215]",
			"value": "",
			"enabled": true
		},
		{
			"key": "Name[215]",
			"value": "",
			"enabled": true
		},
		{
			"key": "URL[215]",
			"value": "",
			"enabled": true
		},
		{
			"key": "Country[216]",
			"value": "",
			"enabled": true
		},
		{
			"key": "Name[216]",
			"value": "",
			"enabled": true
		},
		{
			"key": "URL[216]",
			"value": "",
			"enabled": true
		},
		{
			"key": "Country[217]",
			"value": "",
			"enabled": true
		},
		{
			"key": "Name[217]",
			"value": "",
			"enabled": true
		},
		{
			"key": "URL[217]",
			"value": "",
			"enabled": true
		},
		{
			"key": "Country[218]",
			"value": "",
			"enabled": true
		},
		{
			"key": "Name[218]",
			"value": "",
			"enabled": true
		},
		{
			"key": "URL[218]",
			"value": "",
			"enabled": true
		},
		{
			"key": "Country[219]",
			"value": "",
			"enabled": true
		},
		{
			"key": "Name[219]",
			"value": "",
			"enabled": true
		},
		{
			"key": "URL[219]",
			"value": "",
			"enabled": true
		},
		{
			"key": "Country[220]",
			"value": "",
			"enabled": true
		},
		{
			"key": "Name[220]",
			"value": "",
			"enabled": true
		},
		{
			"key": "URL[220]",
			"value": "",
			"enabled": true
		},
		{
			"key": "Country[221]",
			"value": "",
			"enabled": true
		},
		{
			"key": "Name[221]",
			"value": "",
			"enabled": true
		},
		{
			"key": "URL[221]",
			"value": "",
			"enabled": true
		},
		{
			"key": "Country[222]",
			"value": "",
			"enabled": true
		},
		{
			"key": "Name[222]",
			"value": "",
			"enabled": true
		},
		{
			"key": "URL[222]",
			"value": "",
			"enabled": true
		},
		{
			"key": "Country[223]",
			"value": "",
			"enabled": true
		},
		{
			"key": "Name[223]",
			"value": "",
			"enabled": true
		},
		{
			"key": "URL[223]",
			"value": "",
			"enabled": true
		},
		{
			"key": "Country[224]",
			"value": "",
			"enabled": true
		},
		{
			"key": "Name[224]",
			"value": "",
			"enabled": true
		},
		{
			"key": "URL[224]",
			"value": "",
			"enabled": true
		},
		{
			"key": "Country[225]",
			"value": "",
			"enabled": true
		},
		{
			"key": "Name[225]",
			"value": "",
			"enabled": true
		},
		{
			"key": "URL[225]",
			"value": "",
			"enabled": true
		},
		{
			"key": "Country[226]",
			"value": "",
			"enabled": true
		},
		{
			"key": "Name[226]",
			"value": "",
			"enabled": true
		},
		{
			"key": "URL[226]",
			"value": "",
			"enabled": true
		},
		{
			"key": "Country[227]",
			"value": "",
			"enabled": true
		},
		{
			"key": "Name[227]",
			"value": "",
			"enabled": true
		},
		{
			"key": "URL[227]",
			"value": "",
			"enabled": true
		},
		{
			"key": "Country[228]",
			"value": "",
			"enabled": true
		},
		{
			"key": "Name[228]",
			"value": "",
			"enabled": true
		},
		{
			"key": "URL[228]",
			"value": "",
			"enabled": true
		},
		{
			"key": "Country[229]",
			"value": "",
			"enabled": true
		},
		{
			"key": "Name[229]",
			"value": "",
			"enabled": true
		},
		{
			"key": "URL[229]",
			"value": "",
			"enabled": true
		},
		{
			"key": "Country[230]",
			"value": "",
			"enabled": true
		},
		{
			"key": "Name[230]",
			"value": "",
			"enabled": true
		},
		{
			"key": "URL[230]",
			"value": "",
			"enabled": true
		},
		{
			"key": "Country[231]",
			"value": "",
			"enabled": true
		},
		{
			"key": "Name[231]",
			"value": "",
			"enabled": true
		},
		{
			"key": "URL[231]",
			"value": "",
			"enabled": true
		},
		{
			"key": "Country[232]",
			"value": "",
			"enabled": true
		},
		{
			"key": "Name[232]",
			"value": "",
			"enabled": true
		},
		{
			"key": "URL[232]",
			"value": "",
			"enabled": true
		},
		{
			"key": "Country[233]",
			"value": "",
			"enabled": true
		},
		{
			"key": "Name[233]",
			"value": "",
			"enabled": true
		},
		{
			"key": "URL[233]",
			"value": "",
			"enabled": true
		},
		{
			"key": "Country[234]",
			"value": "",
			"enabled": true
		},
		{
			"key": "Name[234]",
			"value": "",
			"enabled": true
		},
		{
			"key": "URL[234]",
			"value": "",
			"enabled": true
		},
		{
			"key": "Country[235]",
			"value": "",
			"enabled": true
		},
		{
			"key": "Name[235]",
			"value": "",
			"enabled": true
		},
		{
			"key": "URL[235]",
			"value": "",
			"enabled": true
		},
		{
			"key": "Country[236]",
			"value": "",
			"enabled": true
		},
		{
			"key": "Name[236]",
			"value": "",
			"enabled": true
		},
		{
			"key": "URL[236]",
			"value": "",
			"enabled": true
		},
		{
			"key": "Country[237]",
			"value": "",
			"enabled": true
		},
		{
			"key": "Name[237]",
			"value": "",
			"enabled": true
		},
		{
			"key": "URL[237]",
			"value": "",
			"enabled": true
		},
		{
			"key": "Country[238]",
			"value": "",
			"enabled": true
		},
		{
			"key": "Name[238]",
			"value": "",
			"enabled": true
		},
		{
			"key": "URL[238]",
			"value": "",
			"enabled": true
		},
		{
			"key": "Country[239]",
			"value": "",
			"enabled": true
		},
		{
			"key": "Name[239]",
			"value": "",
			"enabled": true
		},
		{
			"key": "URL[239]",
			"value": "",
			"enabled": true
		},
		{
			"key": "Country[240]",
			"value": "",
			"enabled": true
		},
		{
			"key": "Name[240]",
			"value": "",
			"enabled": true
		},
		{
			"key": "URL[240]",
			"value": "",
			"enabled": true
		},
		{
			"key": "Country[241]",
			"value": "",
			"enabled": true
		},
		{
			"key": "Name[241]",
			"value": "",
			"enabled": true
		},
		{
			"key": "URL[241]",
			"value": "",
			"enabled": true
		},
		{
			"key": "Country[242]",
			"value": "",
			"enabled": true
		},
		{
			"key": "Name[242]",
			"value": "",
			"enabled": true
		},
		{
			"key": "URL[242]",
			"value": "",
			"enabled": true
		},
		{
			"key": "Country[243]",
			"value": "",
			"enabled": true
		},
		{
			"key": "Name[243]",
			"value": "",
			"enabled": true
		},
		{
			"key": "URL[243]",
			"value": "",
			"enabled": true
		},
		{
			"key": "Country[244]",
			"value": "",
			"enabled": true
		},
		{
			"key": "Name[244]",
			"value": "",
			"enabled": true
		},
		{
			"key": "URL[244]",
			"value": "",
			"enabled": true
		},
		{
			"key": "Country[245]",
			"value": "",
			"enabled": true
		},
		{
			"key": "Name[245]",
			"value": "",
			"enabled": true
		},
		{
			"key": "URL[245]",
			"value": "",
			"enabled": true
		},
		{
			"key": "Country[246]",
			"value": "",
			"enabled": true
		},
		{
			"key": "Name[246]",
			"value": "",
			"enabled": true
		},
		{
			"key": "URL[246]",
			"value": "",
			"enabled": true
		},
		{
			"key": "Country[247]",
			"value": "",
			"enabled": true
		},
		{
			"key": "Name[247]",
			"value": "",
			"enabled": true
		},
		{
			"key": "URL[247]",
			"value": "",
			"enabled": true
		},
		{
			"key": "Country[248]",
			"value": "",
			"enabled": true
		},
		{
			"key": "Name[248]",
			"value": "",
			"enabled": true
		},
		{
			"key": "URL[248]",
			"value": "",
			"enabled": true
		},
		{
			"key": "Country[249]",
			"value": "",
			"enabled": true
		},
		{
			"key": "Name[249]",
			"value": "",
			"enabled": true
		},
		{
			"key": "URL[249]",
			"value": "",
			"enabled": true
		},
		{
			"key": "Country[250]",
			"value": "",
			"enabled": true
		},
		{
			"key": "Name[250]",
			"value": "",
			"enabled": true
		},
		{
			"key": "URL[250]",
			"value": "",
			"enabled": true
		},
		{
			"key": "Country[251]",
			"value": "",
			"enabled": true
		},
		{
			"key": "Name[251]",
			"value": "",
			"enabled": true
		},
		{
			"key": "URL[251]",
			"value": "",
			"enabled": true
		},
		{
			"key": "Country[252]",
			"value": "",
			"enabled": true
		},
		{
			"key": "Name[252]",
			"value": "",
			"enabled": true
		},
		{
			"key": "URL[252]",
			"value": "",
			"enabled": true
		},
		{
			"key": "Country[253]",
			"value": "",
			"enabled": true
		},
		{
			"key": "Name[253]",
			"value": "",
			"enabled": true
		},
		{
			"key": "URL[253]",
			"value": "",
			"enabled": true
		},
		{
			"key": "Country[254]",
			"value": "",
			"enabled": true
		},
		{
			"key": "Name[254]",
			"value": "",
			"enabled": true
		},
		{
			"key": "URL[254]",
			"value": "",
			"enabled": true
		},
		{
			"key": "Country[255]",
			"value": "",
			"enabled": true
		},
		{
			"key": "Name[255]",
			"value": "",
			"enabled": true
		},
		{
			"key": "URL[255]",
			"value": "",
			"enabled": true
		},
		{
			"key": "Country[256]",
			"value": "",
			"enabled": true
		},
		{
			"key": "Name[256]",
			"value": "",
			"enabled": true
		},
		{
			"key": "URL[256]",
			"value": "",
			"enabled": true
		},
		{
			"key": "Country[257]",
			"value": "",
			"enabled": true
		},
		{
			"key": "Name[257]",
			"value": "",
			"enabled": true
		},
		{
			"key": "URL[257]",
			"value": "",
			"enabled": true
		},
		{
			"key": "Country[258]",
			"value": "",
			"enabled": true
		},
		{
			"key": "Name[258]",
			"value": "",
			"enabled": true
		},
		{
			"key": "URL[258]",
			"value": "",
			"enabled": true
		},
		{
			"key": "Country[259]",
			"value": "",
			"enabled": true
		},
		{
			"key": "Name[259]",
			"value": "",
			"enabled": true
		},
		{
			"key": "URL[259]",
			"value": "",
			"enabled": true
		},
		{
			"key": "Country[260]",
			"value": "",
			"enabled": true
		},
		{
			"key": "Name[260]",
			"value": "",
			"enabled": true
		},
		{
			"key": "URL[260]",
			"value": "",
			"enabled": true
		},
		{
			"key": "Country[261]",
			"value": "",
			"enabled": true
		},
		{
			"key": "Name[261]",
			"value": "",
			"enabled": true
		},
		{
			"key": "URL[261]",
			"value": "",
			"enabled": true
		},
		{
			"key": "Country[262]",
			"value": "",
			"enabled": true
		},
		{
			"key": "Name[262]",
			"value": "",
			"enabled": true
		},
		{
			"key": "URL[262]",
			"value": "",
			"enabled": true
		},
		{
			"key": "Country[263]",
			"value": "",
			"enabled": true
		},
		{
			"key": "Name[263]",
			"value": "",
			"enabled": true
		},
		{
			"key": "URL[263]",
			"value": "",
			"enabled": true
		},
		{
			"key": "Country[264]",
			"value": "",
			"enabled": true
		},
		{
			"key": "Name[264]",
			"value": "",
			"enabled": true
		},
		{
			"key": "URL[264]",
			"value": "",
			"enabled": true
		},
		{
			"key": "Country[265]",
			"value": "",
			"enabled": true
		},
		{
			"key": "Name[265]",
			"value": "",
			"enabled": true
		},
		{
			"key": "URL[265]",
			"value": "",
			"enabled": true
		},
		{
			"key": "Country[266]",
			"value": "",
			"enabled": true
		},
		{
			"key": "Name[266]",
			"value": "",
			"enabled": true
		},
		{
			"key": "URL[266]",
			"value": "",
			"enabled": true
		},
		{
			"key": "Country[267]",
			"value": "",
			"enabled": true
		},
		{
			"key": "Name[267]",
			"value": "",
			"enabled": true
		},
		{
			"key": "URL[267]",
			"value": "",
			"enabled": true
		},
		{
			"key": "Country[268]",
			"value": "",
			"enabled": true
		},
		{
			"key": "Name[268]",
			"value": "",
			"enabled": true
		},
		{
			"key": "URL[268]",
			"value": "",
			"enabled": true
		},
		{
			"key": "Country[269]",
			"value": "",
			"enabled": true
		},
		{
			"key": "Name[269]",
			"value": "",
			"enabled": true
		},
		{
			"key": "URL[269]",
			"value": "",
			"enabled": true
		},
		{
			"key": "Country[270]",
			"value": "",
			"enabled": true
		},
		{
			"key": "Name[270]",
			"value": "",
			"enabled": true
		},
		{
			"key": "URL[270]",
			"value": "",
			"enabled": true
		},
		{
			"key": "Country[271]",
			"value": "",
			"enabled": true
		},
		{
			"key": "Name[271]",
			"value": "",
			"enabled": true
		},
		{
			"key": "URL[271]",
			"value": "",
			"enabled": true
		},
		{
			"key": "Country[272]",
			"value": "",
			"enabled": true
		},
		{
			"key": "Name[272]",
			"value": "",
			"enabled": true
		},
		{
			"key": "URL[272]",
			"value": "",
			"enabled": true
		},
		{
			"key": "Country[273]",
			"value": "",
			"enabled": true
		},
		{
			"key": "Name[273]",
			"value": "",
			"enabled": true
		},
		{
			"key": "URL[273]",
			"value": "",
			"enabled": true
		},
		{
			"key": "Country[274]",
			"value": "",
			"enabled": true
		},
		{
			"key": "Name[274]",
			"value": "",
			"enabled": true
		},
		{
			"key": "URL[274]",
			"value": "",
			"enabled": true
		},
		{
			"key": "Country[275]",
			"value": "",
			"enabled": true
		},
		{
			"key": "Name[275]",
			"value": "",
			"enabled": true
		},
		{
			"key": "URL[275]",
			"value": "",
			"enabled": true
		},
		{
			"key": "Country[276]",
			"value": "",
			"enabled": true
		},
		{
			"key": "Name[276]",
			"value": "",
			"enabled": true
		},
		{
			"key": "URL[276]",
			"value": "",
			"enabled": true
		},
		{
			"key": "Country[277]",
			"value": "",
			"enabled": true
		},
		{
			"key": "Name[277]",
			"value": "",
			"enabled": true
		},
		{
			"key": "URL[277]",
			"value": "",
			"enabled": true
		},
		{
			"key": "Country[278]",
			"value": "",
			"enabled": true
		},
		{
			"key": "Name[278]",
			"value": "",
			"enabled": true
		},
		{
			"key": "URL[278]",
			"value": "",
			"enabled": true
		},
		{
			"key": "Country[279]",
			"value": "",
			"enabled": true
		},
		{
			"key": "Name[279]",
			"value": "",
			"enabled": true
		},
		{
			"key": "URL[279]",
			"value": "",
			"enabled": true
		},
		{
			"key": "Country[280]",
			"value": "",
			"enabled": true
		},
		{
			"key": "Name[280]",
			"value": "",
			"enabled": true
		},
		{
			"key": "URL[280]",
			"value": "",
			"enabled": true
		},
		{
			"key": "Country[281]",
			"value": "",
			"enabled": true
		},
		{
			"key": "Name[281]",
			"value": "",
			"enabled": true
		},
		{
			"key": "URL[281]",
			"value": "",
			"enabled": true
		},
		{
			"key": "Country[282]",
			"value": "",
			"enabled": true
		},
		{
			"key": "Name[282]",
			"value": "",
			"enabled": true
		},
		{
			"key": "URL[282]",
			"value": "",
			"enabled": true
		},
		{
			"key": "Country[283]",
			"value": "",
			"enabled": true
		},
		{
			"key": "Name[283]",
			"value": "",
			"enabled": true
		},
		{
			"key": "URL[283]",
			"value": "",
			"enabled": true
		},
		{
			"key": "Country[284]",
			"value": "",
			"enabled": true
		},
		{
			"key": "Name[284]",
			"value": "",
			"enabled": true
		},
		{
			"key": "URL[284]",
			"value": "",
			"enabled": true
		},
		{
			"key": "Country[285]",
			"value": "",
			"enabled": true
		},
		{
			"key": "Name[285]",
			"value": "",
			"enabled": true
		},
		{
			"key": "URL[285]",
			"value": "",
			"enabled": true
		},
		{
			"key": "Country[286]",
			"value": "",
			"enabled": true
		},
		{
			"key": "Name[286]",
			"value": "",
			"enabled": true
		},
		{
			"key": "URL[286]",
			"value": "",
			"enabled": true
		},
		{
			"key": "Country[287]",
			"value": "",
			"enabled": true
		},
		{
			"key": "Name[287]",
			"value": "",
			"enabled": true
		},
		{
			"key": "URL[287]",
			"value": "",
			"enabled": true
		},
		{
			"key": "Country[288]",
			"value": "",
			"enabled": true
		},
		{
			"key": "Name[288]",
			"value": "",
			"enabled": true
		},
		{
			"key": "URL[288]",
			"value": "",
			"enabled": true
		},
		{
			"key": "Country[289]",
			"value": "",
			"enabled": true
		},
		{
			"key": "Name[289]",
			"value": "",
			"enabled": true
		},
		{
			"key": "URL[289]",
			"value": "",
			"enabled": true
		},
		{
			"key": "Country[290]",
			"value": "",
			"enabled": true
		},
		{
			"key": "Name[290]",
			"value": "",
			"enabled": true
		},
		{
			"key": "URL[290]",
			"value": "",
			"enabled": true
		},
		{
			"key": "Country[291]",
			"value": "",
			"enabled": true
		},
		{
			"key": "Name[291]",
			"value": "",
			"enabled": true
		},
		{
			"key": "URL[291]",
			"value": "",
			"enabled": true
		},
		{
			"key": "Country[292]",
			"value": "",
			"enabled": true
		},
		{
			"key": "Name[292]",
			"value": "",
			"enabled": true
		},
		{
			"key": "URL[292]",
			"value": "",
			"enabled": true
		},
		{
			"key": "Country[293]",
			"value": "",
			"enabled": true
		},
		{
			"key": "Name[293]",
			"value": "",
			"enabled": true
		},
		{
			"key": "URL[293]",
			"value": "",
			"enabled": true
		},
		{
			"key": "Country[294]",
			"value": "",
			"enabled": true
		},
		{
			"key": "Name[294]",
			"value": "",
			"enabled": true
		},
		{
			"key": "URL[294]",
			"value": "",
			"enabled": true
		},
		{
			"key": "Country[295]",
			"value": "",
			"enabled": true
		},
		{
			"key": "Name[295]",
			"value": "",
			"enabled": true
		},
		{
			"key": "URL[295]",
			"value": "",
			"enabled": true
		},
		{
			"key": "Country[296]",
			"value": "",
			"enabled": true
		},
		{
			"key": "Name[296]",
			"value": "",
			"enabled": true
		},
		{
			"key": "URL[296]",
			"value": "",
			"enabled": true
		},
		{
			"key": "Country[297]",
			"value": "",
			"enabled": true
		},
		{
			"key": "Name[297]",
			"value": "",
			"enabled": true
		},
		{
			"key": "URL[297]",
			"value": "",
			"enabled": true
		},
		{
			"key": "Country[298]",
			"value": "",
			"enabled": true
		},
		{
			"key": "Name[298]",
			"value": "",
			"enabled": true
		},
		{
			"key": "URL[298]",
			"value": "",
			"enabled": true
		},
		{
			"key": "Country[299]",
			"value": "",
			"enabled": true
		},
		{
			"key": "Name[299]",
			"value": "",
			"enabled": true
		},
		{
			"key": "URL[299]",
			"value": "",
			"enabled": true
		},
		{
			"key": "Country[300]",
			"value": "",
			"enabled": true
		},
		{
			"key": "Name[300]",
			"value": "",
			"enabled": true
		},
		{
			"key": "URL[300]",
			"value": "",
			"enabled": true
		},
		{
			"key": "Country[301]",
			"value": "",
			"enabled": true
		},
		{
			"key": "Name[301]",
			"value": "",
			"enabled": true
		},
		{
			"key": "URL[301]",
			"value": "",
			"enabled": true
		},
		{
			"key": "Country[302]",
			"value": "",
			"enabled": true
		},
		{
			"key": "Name[302]",
			"value": "",
			"enabled": true
		},
		{
			"key": "URL[302]",
			"value": "",
			"enabled": true
		},
		{
			"key": "Country[303]",
			"value": "",
			"enabled": true
		},
		{
			"key": "Name[303]",
			"value": "",
			"enabled": true
		},
		{
			"key": "URL[303]",
			"value": "",
			"enabled": true
		},
		{
			"key": "Country[304]",
			"value": "",
			"enabled": true
		},
		{
			"key": "Name[304]",
			"value": "",
			"enabled": true
		},
		{
			"key": "URL[304]",
			"value": "",
			"enabled": true
		},
		{
			"key": "Country[305]",
			"value": "",
			"enabled": true
		},
		{
			"key": "Name[305]",
			"value": "",
			"enabled": true
		},
		{
			"key": "URL[305]",
			"value": "",
			"enabled": true
		},
		{
			"key": "Country[306]",
			"value": "",
			"enabled": true
		},
		{
			"key": "Name[306]",
			"value": "",
			"enabled": true
		},
		{
			"key": "URL[306]",
			"value": "",
			"enabled": true
		},
		{
			"key": "Country[307]",
			"value": "",
			"enabled": true
		},
		{
			"key": "Name[307]",
			"value": "",
			"enabled": true
		},
		{
			"key": "URL[307]",
			"value": "",
			"enabled": true
		},
		{
			"key": "Country[308]",
			"value": "",
			"enabled": true
		},
		{
			"key": "Name[308]",
			"value": "",
			"enabled": true
		},
		{
			"key": "URL[308]",
			"value": "",
			"enabled": true
		},
		{
			"key": "Country[309]",
			"value": "",
			"enabled": true
		},
		{
			"key": "Name[309]",
			"value": "",
			"enabled": true
		},
		{
			"key": "URL[309]",
			"value": "",
			"enabled": true
		},
		{
			"key": "Country[310]",
			"value": "",
			"enabled": true
		},
		{
			"key": "Name[310]",
			"value": "",
			"enabled": true
		},
		{
			"key": "URL[310]",
			"value": "",
			"enabled": true
		},
		{
			"key": "Country[311]",
			"value": "",
			"enabled": true
		},
		{
			"key": "Name[311]",
			"value": "",
			"enabled": true
		},
		{
			"key": "URL[311]",
			"value": "",
			"enabled": true
		},
		{
			"key": "Country[312]",
			"value": "",
			"enabled": true
		},
		{
			"key": "Name[312]",
			"value": "",
			"enabled": true
		},
		{
			"key": "URL[312]",
			"value": "",
			"enabled": true
		},
		{
			"key": "Country[313]",
			"value": "",
			"enabled": true
		},
		{
			"key": "Name[313]",
			"value": "",
			"enabled": true
		},
		{
			"key": "URL[313]",
			"value": "",
			"enabled": true
		},
		{
			"key": "Country[314]",
			"value": "",
			"enabled": true
		},
		{
			"key": "Name[314]",
			"value": "",
			"enabled": true
		},
		{
			"key": "URL[314]",
			"value": "",
			"enabled": true
		},
		{
			"key": "Country[315]",
			"value": "",
			"enabled": true
		},
		{
			"key": "Name[315]",
			"value": "",
			"enabled": true
		},
		{
			"key": "URL[315]",
			"value": "",
			"enabled": true
		},
		{
			"key": "Country[316]",
			"value": "",
			"enabled": true
		},
		{
			"key": "Name[316]",
			"value": "",
			"enabled": true
		},
		{
			"key": "URL[316]",
			"value": "",
			"enabled": true
		},
		{
			"key": "Country[317]",
			"value": "",
			"enabled": true
		},
		{
			"key": "Name[317]",
			"value": "",
			"enabled": true
		},
		{
			"key": "URL[317]",
			"value": "",
			"enabled": true
		},
		{
			"key": "Country[318]",
			"value": "",
			"enabled": true
		},
		{
			"key": "Name[318]",
			"value": "",
			"enabled": true
		},
		{
			"key": "URL[318]",
			"value": "",
			"enabled": true
		},
		{
			"key": "Country[319]",
			"value": "",
			"enabled": true
		},
		{
			"key": "Name[319]",
			"value": "",
			"enabled": true
		},
		{
			"key": "URL[319]",
			"value": "",
			"enabled": true
		},
		{
			"key": "Country[320]",
			"value": "",
			"enabled": true
		},
		{
			"key": "Name[320]",
			"value": "",
			"enabled": true
		},
		{
			"key": "URL[320]",
			"value": "",
			"enabled": true
		},
		{
			"key": "Country[321]",
			"value": "",
			"enabled": true
		},
		{
			"key": "Name[321]",
			"value": "",
			"enabled": true
		},
		{
			"key": "URL[321]",
			"value": "",
			"enabled": true
		},
		{
			"key": "Country[322]",
			"value": "",
			"enabled": true
		},
		{
			"key": "Name[322]",
			"value": "",
			"enabled": true
		},
		{
			"key": "URL[322]",
			"value": "",
			"enabled": true
		},
		{
			"key": "Country[323]",
			"value": "",
			"enabled": true
		},
		{
			"key": "Name[323]",
			"value": "",
			"enabled": true
		},
		{
			"key": "URL[323]",
			"value": "",
			"enabled": true
		},
		{
			"key": "Country[324]",
			"value": "",
			"enabled": true
		},
		{
			"key": "Name[324]",
			"value": "",
			"enabled": true
		},
		{
			"key": "URL[324]",
			"value": "",
			"enabled": true
		},
		{
			"key": "Country[325]",
			"value": "",
			"enabled": true
		},
		{
			"key": "Name[325]",
			"value": "",
			"enabled": true
		},
		{
			"key": "URL[325]",
			"value": "",
			"enabled": true
		},
		{
			"key": "Country[326]",
			"value": "",
			"enabled": true
		},
		{
			"key": "Name[326]",
			"value": "",
			"enabled": true
		},
		{
			"key": "URL[326]",
			"value": "",
			"enabled": true
		},
		{
			"key": "Country[327]",
			"value": "",
			"enabled": true
		},
		{
			"key": "Name[327]",
			"value": "",
			"enabled": true
		},
		{
			"key": "URL[327]",
			"value": "",
			"enabled": true
		},
		{
			"key": "Country[328]",
			"value": "",
			"enabled": true
		},
		{
			"key": "Name[328]",
			"value": "",
			"enabled": true
		},
		{
			"key": "URL[328]",
			"value": "",
			"enabled": true
		},
		{
			"key": "Country[329]",
			"value": "",
			"enabled": true
		},
		{
			"key": "Name[329]",
			"value": "",
			"enabled": true
		},
		{
			"key": "URL[329]",
			"value": "",
			"enabled": true
		},
		{
			"key": "Country[330]",
			"value": "",
			"enabled": true
		},
		{
			"key": "Name[330]",
			"value": "",
			"enabled": true
		},
		{
			"key": "URL[330]",
			"value": "",
			"enabled": true
		},
		{
			"key": "Country[331]",
			"value": "",
			"enabled": true
		},
		{
			"key": "Name[331]",
			"value": "",
			"enabled": true
		},
		{
			"key": "URL[331]",
			"value": "",
			"enabled": true
		},
		{
			"key": "Country[332]",
			"value": "",
			"enabled": true
		},
		{
			"key": "Name[332]",
			"value": "",
			"enabled": true
		},
		{
			"key": "URL[332]",
			"value": "",
			"enabled": true
		},
		{
			"key": "Country[333]",
			"value": "",
			"enabled": true
		},
		{
			"key": "Name[333]",
			"value": "",
			"enabled": true
		},
		{
			"key": "URL[333]",
			"value": "",
			"enabled": true
		},
		{
			"key": "Country[334]",
			"value": "",
			"enabled": true
		},
		{
			"key": "Name[334]",
			"value": "",
			"enabled": true
		},
		{
			"key": "URL[334]",
			"value": "",
			"enabled": true
		},
		{
			"key": "Country[335]",
			"value": "",
			"enabled": true
		},
		{
			"key": "Name[335]",
			"value": "",
			"enabled": true
		},
		{
			"key": "URL[335]",
			"value": "",
			"enabled": true
		},
		{
			"key": "Country[336]",
			"value": "",
			"enabled": true
		},
		{
			"key": "Name[336]",
			"value": "",
			"enabled": true
		},
		{
			"key": "URL[336]",
			"value": "",
			"enabled": true
		},
		{
			"key": "Country[337]",
			"value": "",
			"enabled": true
		},
		{
			"key": "Name[337]",
			"value": "",
			"enabled": true
		},
		{
			"key": "URL[337]",
			"value": "",
			"enabled": true
		},
		{
			"key": "Country[338]",
			"value": "",
			"enabled": true
		},
		{
			"key": "Name[338]",
			"value": "",
			"enabled": true
		},
		{
			"key": "URL[338]",
			"value": "",
			"enabled": true
		},
		{
			"key": "Country[339]",
			"value": "",
			"enabled": true
		},
		{
			"key": "Name[339]",
			"value": "",
			"enabled": true
		},
		{
			"key": "URL[339]",
			"value": "",
			"enabled": true
		},
		{
			"key": "Country[340]",
			"value": "",
			"enabled": true
		},
		{
			"key": "Name[340]",
			"value": "",
			"enabled": true
		},
		{
			"key": "URL[340]",
			"value": "",
			"enabled": true
		},
		{
			"key": "Country[341]",
			"value": "",
			"enabled": true
		},
		{
			"key": "Name[341]",
			"value": "",
			"enabled": true
		},
		{
			"key": "URL[341]",
			"value": "",
			"enabled": true
		},
		{
			"key": "Country[342]",
			"value": "",
			"enabled": true
		},
		{
			"key": "Name[342]",
			"value": "",
			"enabled": true
		},
		{
			"key": "URL[342]",
			"value": "",
			"enabled": true
		},
		{
			"key": "Country[343]",
			"value": "",
			"enabled": true
		},
		{
			"key": "Name[343]",
			"value": "",
			"enabled": true
		},
		{
			"key": "URL[343]",
			"value": "",
			"enabled": true
		},
		{
			"key": "Country[344]",
			"value": "",
			"enabled": true
		},
		{
			"key": "Name[344]",
			"value": "",
			"enabled": true
		},
		{
			"key": "URL[344]",
			"value": "",
			"enabled": true
		},
		{
			"key": "Country[345]",
			"value": "",
			"enabled": true
		},
		{
			"key": "Name[345]",
			"value": "",
			"enabled": true
		},
		{
			"key": "URL[345]",
			"value": "",
			"enabled": true
		},
		{
			"key": "Country[346]",
			"value": "",
			"enabled": true
		},
		{
			"key": "Name[346]",
			"value": "",
			"enabled": true
		},
		{
			"key": "URL[346]",
			"value": "",
			"enabled": true
		},
		{
			"key": "Country[347]",
			"value": "",
			"enabled": true
		},
		{
			"key": "Name[347]",
			"value": "",
			"enabled": true
		},
		{
			"key": "URL[347]",
			"value": "",
			"enabled": true
		},
		{
			"key": "Country[348]",
			"value": "",
			"enabled": true
		},
		{
			"key": "Name[348]",
			"value": "",
			"enabled": true
		},
		{
			"key": "URL[348]",
			"value": "",
			"enabled": true
		},
		{
			"key": "Country[349]",
			"value": "",
			"enabled": true
		},
		{
			"key": "Name[349]",
			"value": "",
			"enabled": true
		},
		{
			"key": "URL[349]",
			"value": "",
			"enabled": true
		},
		{
			"key": "Country[350]",
			"value": "",
			"enabled": true
		},
		{
			"key": "Name[350]",
			"value": "",
			"enabled": true
		},
		{
			"key": "URL[350]",
			"value": "",
			"enabled": true
		},
		{
			"key": "Country[351]",
			"value": "",
			"enabled": true
		},
		{
			"key": "Name[351]",
			"value": "",
			"enabled": true
		},
		{
			"key": "URL[351]",
			"value": "",
			"enabled": true
		},
		{
			"key": "Country[352]",
			"value": "",
			"enabled": true
		},
		{
			"key": "Name[352]",
			"value": "",
			"enabled": true
		},
		{
			"key": "URL[352]",
			"value": "",
			"enabled": true
		},
		{
			"key": "Country[353]",
			"value": "",
			"enabled": true
		},
		{
			"key": "Name[353]",
			"value": "",
			"enabled": true
		},
		{
			"key": "URL[353]",
			"value": "",
			"enabled": true
		},
		{
			"key": "Country[354]",
			"value": "",
			"enabled": true
		},
		{
			"key": "Name[354]",
			"value": "",
			"enabled": true
		},
		{
			"key": "URL[354]",
			"value": "",
			"enabled": true
		},
		{
			"key": "Country[355]",
			"value": "",
			"enabled": true
		},
		{
			"key": "Name[355]",
			"value": "",
			"enabled": true
		},
		{
			"key": "URL[355]",
			"value": "",
			"enabled": true
		},
		{
			"key": "Country[356]",
			"value": "",
			"enabled": true
		},
		{
			"key": "Name[356]",
			"value": "",
			"enabled": true
		},
		{
			"key": "URL[356]",
			"value": "",
			"enabled": true
		},
		{
			"key": "Country[357]",
			"value": "",
			"enabled": true
		},
		{
			"key": "Name[357]",
			"value": "",
			"enabled": true
		},
		{
			"key": "URL[357]",
			"value": "",
			"enabled": true
		},
		{
			"key": "Country[358]",
			"value": "",
			"enabled": true
		},
		{
			"key": "Name[358]",
			"value": "",
			"enabled": true
		},
		{
			"key": "URL[358]",
			"value": "",
			"enabled": true
		},
		{
			"key": "Country[359]",
			"value": "",
			"enabled": true
		},
		{
			"key": "Name[359]",
			"value": "",
			"enabled": true
		},
		{
			"key": "URL[359]",
			"value": "",
			"enabled": true
		},
		{
			"key": "Country[360]",
			"value": "",
			"enabled": true
		},
		{
			"key": "Name[360]",
			"value": "",
			"enabled": true
		},
		{
			"key": "URL[360]",
			"value": "",
			"enabled": true
		},
		{
			"key": "Country[361]",
			"value": "",
			"enabled": true
		},
		{
			"key": "Name[361]",
			"value": "",
			"enabled": true
		},
		{
			"key": "URL[361]",
			"value": "",
			"enabled": true
		},
		{
			"key": "Country[362]",
			"value": "",
			"enabled": true
		},
		{
			"key": "Name[362]",
			"value": "",
			"enabled": true
		},
		{
			"key": "URL[362]",
			"value": "",
			"enabled": true
		},
		{
			"key": "Country[363]",
			"value": "",
			"enabled": true
		},
		{
			"key": "Name[363]",
			"value": "",
			"enabled": true
		},
		{
			"key": "URL[363]",
			"value": "",
			"enabled": true
		},
		{
			"key": "Country[364]",
			"value": "",
			"enabled": true
		},
		{
			"key": "Name[364]",
			"value": "",
			"enabled": true
		},
		{
			"key": "URL[364]",
			"value": "",
			"enabled": true
		},
		{
			"key": "Country[365]",
			"value": "",
			"enabled": true
		},
		{
			"key": "Name[365]",
			"value": "",
			"enabled": true
		},
		{
			"key": "URL[365]",
			"value": "",
			"enabled": true
		},
		{
			"key": "Country[366]",
			"value": "",
			"enabled": true
		},
		{
			"key": "Name[366]",
			"value": "",
			"enabled": true
		},
		{
			"key": "URL[366]",
			"value": "",
			"enabled": true
		},
		{
			"key": "Country[367]",
			"value": "",
			"enabled": true
		},
		{
			"key": "Name[367]",
			"value": "",
			"enabled": true
		},
		{
			"key": "URL[367]",
			"value": "",
			"enabled": true
		},
		{
			"key": "Country[368]",
			"value": "",
			"enabled": true
		},
		{
			"key": "Name[368]",
			"value": "",
			"enabled": true
		},
		{
			"key": "URL[368]",
			"value": "",
			"enabled": true
		},
		{
			"key": "Country[369]",
			"value": "",
			"enabled": true
		},
		{
			"key": "Name[369]",
			"value": "",
			"enabled": true
		},
		{
			"key": "URL[369]",
			"value": "",
			"enabled": true
		},
		{
			"key": "Country[370]",
			"value": "",
			"enabled": true
		},
		{
			"key": "Name[370]",
			"value": "",
			"enabled": true
		},
		{
			"key": "URL[370]",
			"value": "",
			"enabled": true
		},
		{
			"key": "Country[371]",
			"value": "",
			"enabled": true
		},
		{
			"key": "Name[371]",
			"value": "",
			"enabled": true
		},
		{
			"key": "URL[371]",
			"value": "",
			"enabled": true
		},
		{
			"key": "Country[372]",
			"value": "",
			"enabled": true
		},
		{
			"key": "Name[372]",
			"value": "",
			"enabled": true
		},
		{
			"key": "URL[372]",
			"value": "",
			"enabled": true
		},
		{
			"key": "Country[373]",
			"value": "",
			"enabled": true
		},
		{
			"key": "Name[373]",
			"value": "",
			"enabled": true
		},
		{
			"key": "URL[373]",
			"value": "",
			"enabled": true
		},
		{
			"key": "Country[374]",
			"value": "",
			"enabled": true
		},
		{
			"key": "Name[374]",
			"value": "",
			"enabled": true
		},
		{
			"key": "URL[374]",
			"value": "",
			"enabled": true
		},
		{
			"key": "Country[375]",
			"value": "",
			"enabled": true
		},
		{
			"key": "Name[375]",
			"value": "",
			"enabled": true
		},
		{
			"key": "URL[375]",
			"value": "",
			"enabled": true
		},
		{
			"key": "Country[376]",
			"value": "",
			"enabled": true
		},
		{
			"key": "Name[376]",
			"value": "",
			"enabled": true
		},
		{
			"key": "URL[376]",
			"value": "",
			"enabled": true
		},
		{
			"key": "Country[377]",
			"value": "",
			"enabled": true
		},
		{
			"key": "Name[377]",
			"value": "",
			"enabled": true
		},
		{
			"key": "URL[377]",
			"value": "",
			"enabled": true
		},
		{
			"key": "Country[378]",
			"value": "",
			"enabled": true
		},
		{
			"key": "Name[378]",
			"value": "",
			"enabled": true
		},
		{
			"key": "URL[378]",
			"value": "",
			"enabled": true
		},
		{
			"key": "Country[379]",
			"value": "",
			"enabled": true
		},
		{
			"key": "Name[379]",
			"value": "",
			"enabled": true
		},
		{
			"key": "URL[379]",
			"value": "",
			"enabled": true
		},
		{
			"key": "Country[380]",
			"value": "",
			"enabled": true
		},
		{
			"key": "Name[380]",
			"value": "",
			"enabled": true
		},
		{
			"key": "URL[380]",
			"value": "",
			"enabled": true
		},
		{
			"key": "Country[381]",
			"value": "",
			"enabled": true
		},
		{
			"key": "Name[381]",
			"value": "",
			"enabled": true
		},
		{
			"key": "URL[381]",
			"value": "",
			"enabled": true
		},
		{
			"key": "Country[382]",
			"value": "",
			"enabled": true
		},
		{
			"key": "Name[382]",
			"value": "",
			"enabled": true
		},
		{
			"key": "URL[382]",
			"value": "",
			"enabled": true
		},
		{
			"key": "Country[383]",
			"value": "",
			"enabled": true
		},
		{
			"key": "Name[383]",
			"value": "",
			"enabled": true
		},
		{
			"key": "URL[383]",
			"value": "",
			"enabled": true
		},
		{
			"key": "Country[384]",
			"value": "",
			"enabled": true
		},
		{
			"key": "Name[384]",
			"value": "",
			"enabled": true
		},
		{
			"key": "URL[384]",
			"value": "",
			"enabled": true
		},
		{
			"key": "Country[385]",
			"value": "",
			"enabled": true
		},
		{
			"key": "Name[385]",
			"value": "",
			"enabled": true
		},
		{
			"key": "URL[385]",
			"value": "",
			"enabled": true
		},
		{
			"key": "Country[386]",
			"value": "",
			"enabled": true
		},
		{
			"key": "Name[386]",
			"value": "",
			"enabled": true
		},
		{
			"key": "URL[386]",
			"value": "",
			"enabled": true
		},
		{
			"key": "Country[387]",
			"value": "",
			"enabled": true
		},
		{
			"key": "Name[387]",
			"value": "",
			"enabled": true
		},
		{
			"key": "URL[387]",
			"value": "",
			"enabled": true
		},
		{
			"key": "Country[388]",
			"value": "",
			"enabled": true
		},
		{
			"key": "Name[388]",
			"value": "",
			"enabled": true
		},
		{
			"key": "URL[388]",
			"value": "",
			"enabled": true
		},
		{
			"key": "Country[389]",
			"value": "",
			"enabled": true
		},
		{
			"key": "Name[389]",
			"value": "",
			"enabled": true
		},
		{
			"key": "URL[389]",
			"value": "",
			"enabled": true
		},
		{
			"key": "Country[390]",
			"value": "",
			"enabled": true
		},
		{
			"key": "Name[390]",
			"value": "",
			"enabled": true
		},
		{
			"key": "URL[390]",
			"value": "",
			"enabled": true
		},
		{
			"key": "Country[391]",
			"value": "",
			"enabled": true
		},
		{
			"key": "Name[391]",
			"value": "",
			"enabled": true
		},
		{
			"key": "URL[391]",
			"value": "",
			"enabled": true
		},
		{
			"key": "Country[392]",
			"value": "",
			"enabled": true
		},
		{
			"key": "Name[392]",
			"value": "",
			"enabled": true
		},
		{
			"key": "URL[392]",
			"value": "",
			"enabled": true
		},
		{
			"key": "Country[393]",
			"value": "",
			"enabled": true
		},
		{
			"key": "Name[393]",
			"value": "",
			"enabled": true
		},
		{
			"key": "URL[393]",
			"value": "",
			"enabled": true
		},
		{
			"key": "Country[394]",
			"value": "",
			"enabled": true
		},
		{
			"key": "Name[394]",
			"value": "",
			"enabled": true
		},
		{
			"key": "URL[394]",
			"value": "",
			"enabled": true
		},
		{
			"key": "Country[395]",
			"value": "",
			"enabled": true
		},
		{
			"key": "Name[395]",
			"value": "",
			"enabled": true
		},
		{
			"key": "URL[395]",
			"value": "",
			"enabled": true
		},
		{
			"key": "Country[396]",
			"value": "",
			"enabled": true
		},
		{
			"key": "Name[396]",
			"value": "",
			"enabled": true
		},
		{
			"key": "URL[396]",
			"value": "",
			"enabled": true
		},
		{
			"key": "Country[397]",
			"value": "",
			"enabled": true
		},
		{
			"key": "Name[397]",
			"value": "",
			"enabled": true
		},
		{
			"key": "URL[397]",
			"value": "",
			"enabled": true
		},
		{
			"key": "Country[398]",
			"value": "",
			"enabled": true
		},
		{
			"key": "Name[398]",
			"value": "",
			"enabled": true
		},
		{
			"key": "URL[398]",
			"value": "",
			"enabled": true
		},
		{
			"key": "Country[399]",
			"value": "",
			"enabled": true
		},
		{
			"key": "Name[399]",
			"value": "",
			"enabled": true
		},
		{
			"key": "URL[399]",
			"value": "",
			"enabled": true
		},
		{
			"key": "Country[400]",
			"value": "",
			"enabled": true
		},
		{
			"key": "Name[400]",
			"value": "",
			"enabled": true
		},
		{
			"key": "URL[400]",
			"value": "",
			"enabled": true
		},
		{
			"key": "Country[401]",
			"value": "",
			"enabled": true
		},
		{
			"key": "Name[401]",
			"value": "",
			"enabled": true
		},
		{
			"key": "URL[401]",
			"value": "",
			"enabled": true
		},
		{
			"key": "Country[402]",
			"value": "",
			"enabled": true
		},
		{
			"key": "Name[402]",
			"value": "",
			"enabled": true
		},
		{
			"key": "URL[402]",
			"value": "",
			"enabled": true
		},
		{
			"key": "Country[403]",
			"value": "",
			"enabled": true
		},
		{
			"key": "Name[403]",
			"value": "",
			"enabled": true
		},
		{
			"key": "URL[403]",
			"value": "",
			"enabled": true
		},
		{
			"key": "Country[404]",
			"value": "",
			"enabled": true
		},
		{
			"key": "Name[404]",
			"value": "",
			"enabled": true
		},
		{
			"key": "URL[404]",
			"value": "",
			"enabled": true
		},
		{
			"key": "Country[405]",
			"value": "",
			"enabled": true
		},
		{
			"key": "Name[405]",
			"value": "",
			"enabled": true
		},
		{
			"key": "URL[405]",
			"value": "",
			"enabled": true
		},
		{
			"key": "Country[406]",
			"value": "",
			"enabled": true
		},
		{
			"key": "Name[406]",
			"value": "",
			"enabled": true
		},
		{
			"key": "URL[406]",
			"value": "",
			"enabled": true
		},
		{
			"key": "Country[407]",
			"value": "",
			"enabled": true
		},
		{
			"key": "Name[407]",
			"value": "",
			"enabled": true
		},
		{
			"key": "URL[407]",
			"value": "",
			"enabled": true
		},
		{
			"key": "Country[408]",
			"value": "",
			"enabled": true
		},
		{
			"key": "Name[408]",
			"value": "",
			"enabled": true
		},
		{
			"key": "URL[408]",
			"value": "",
			"enabled": true
		},
		{
			"key": "Country[409]",
			"value": "",
			"enabled": true
		},
		{
			"key": "Name[409]",
			"value": "",
			"enabled": true
		},
		{
			"key": "URL[409]",
			"value": "",
			"enabled": true
		},
		{
			"key": "Country[410]",
			"value": "",
			"enabled": true
		},
		{
			"key": "Name[410]",
			"value": "",
			"enabled": true
		},
		{
			"key": "URL[410]",
			"value": "",
			"enabled": true
		},
		{
			"key": "Country[411]",
			"value": "",
			"enabled": true
		},
		{
			"key": "Name[411]",
			"value": "",
			"enabled": true
		},
		{
			"key": "URL[411]",
			"value": "",
			"enabled": true
		},
		{
			"key": "Country[412]",
			"value": "",
			"enabled": true
		},
		{
			"key": "Name[412]",
			"value": "",
			"enabled": true
		},
		{
			"key": "URL[412]",
			"value": "",
			"enabled": true
		},
		{
			"key": "Country[413]",
			"value": "",
			"enabled": true
		},
		{
			"key": "Name[413]",
			"value": "",
			"enabled": true
		},
		{
			"key": "URL[413]",
			"value": "",
			"enabled": true
		},
		{
			"key": "Country[414]",
			"value": "",
			"enabled": true
		},
		{
			"key": "Name[414]",
			"value": "",
			"enabled": true
		},
		{
			"key": "URL[414]",
			"value": "",
			"enabled": true
		},
		{
			"key": "Country[415]",
			"value": "",
			"enabled": true
		},
		{
			"key": "Name[415]",
			"value": "",
			"enabled": true
		},
		{
			"key": "URL[415]",
			"value": "",
			"enabled": true
		},
		{
			"key": "Country[416]",
			"value": "",
			"enabled": true
		},
		{
			"key": "Name[416]",
			"value": "",
			"enabled": true
		},
		{
			"key": "URL[416]",
			"value": "",
			"enabled": true
		},
		{
			"key": "Country[417]",
			"value": "",
			"enabled": true
		},
		{
			"key": "Name[417]",
			"value": "",
			"enabled": true
		},
		{
			"key": "URL[417]",
			"value": "",
			"enabled": true
		},
		{
			"key": "Country[418]",
			"value": "",
			"enabled": true
		},
		{
			"key": "Name[418]",
			"value": "",
			"enabled": true
		},
		{
			"key": "URL[418]",
			"value": "",
			"enabled": true
		},
		{
			"key": "Country[419]",
			"value": "",
			"enabled": true
		},
		{
			"key": "Name[419]",
			"value": "",
			"enabled": true
		},
		{
			"key": "URL[419]",
			"value": "",
			"enabled": true
		},
		{
			"key": "Country[420]",
			"value": "",
			"enabled": true
		},
		{
			"key": "Name[420]",
			"value": "",
			"enabled": true
		},
		{
			"key": "URL[420]",
			"value": "",
			"enabled": true
		},
		{
			"key": "Country[421]",
			"value": "",
			"enabled": true
		},
		{
			"key": "Name[421]",
			"value": "",
			"enabled": true
		},
		{
			"key": "URL[421]",
			"value": "",
			"enabled": true
		},
		{
			"key": "Country[422]",
			"value": "",
			"enabled": true
		},
		{
			"key": "Name[422]",
			"value": "",
			"enabled": true
		},
		{
			"key": "URL[422]",
			"value": "",
			"enabled": true
		},
		{
			"key": "Country[423]",
			"value": "",
			"enabled": true
		},
		{
			"key": "Name[423]",
			"value": "",
			"enabled": true
		},
		{
			"key": "URL[423]",
			"value": "",
			"enabled": true
		},
		{
			"key": "Country[424]",
			"value": "",
			"enabled": true
		},
		{
			"key": "Name[424]",
			"value": "",
			"enabled": true
		},
		{
			"key": "URL[424]",
			"value": "",
			"enabled": true
		},
		{
			"key": "Country[425]",
			"value": "",
			"enabled": true
		},
		{
			"key": "Name[425]",
			"value": "",
			"enabled": true
		},
		{
			"key": "URL[425]",
			"value": "",
			"enabled": true
		},
		{
			"key": "Country[426]",
			"value": "",
			"enabled": true
		},
		{
			"key": "Name[426]",
			"value": "",
			"enabled": true
		},
		{
			"key": "URL[426]",
			"value": "",
			"enabled": true
		},
		{
			"key": "Country[427]",
			"value": "",
			"enabled": true
		},
		{
			"key": "Name[427]",
			"value": "",
			"enabled": true
		},
		{
			"key": "URL[427]",
			"value": "",
			"enabled": true
		},
		{
			"key": "Country[428]",
			"value": "",
			"enabled": true
		},
		{
			"key": "Name[428]",
			"value": "",
			"enabled": true
		},
		{
			"key": "URL[428]",
			"value": "",
			"enabled": true
		},
		{
			"key": "Country[429]",
			"value": "",
			"enabled": true
		},
		{
			"key": "Name[429]",
			"value": "",
			"enabled": true
		},
		{
			"key": "URL[429]",
			"value": "",
			"enabled": true
		},
		{
			"key": "Country[430]",
			"value": "",
			"enabled": true
		},
		{
			"key": "Name[430]",
			"value": "",
			"enabled": true
		},
		{
			"key": "URL[430]",
			"value": "",
			"enabled": true
		},
		{
			"key": "Country[431]",
			"value": "",
			"enabled": true
		},
		{
			"key": "Name[431]",
			"value": "",
			"enabled": true
		},
		{
			"key": "URL[431]",
			"value": "",
			"enabled": true
		},
		{
			"key": "Country[432]",
			"value": "",
			"enabled": true
		},
		{
			"key": "Name[432]",
			"value": "",
			"enabled": true
		},
		{
			"key": "URL[432]",
			"value": "",
			"enabled": true
		},
		{
			"key": "Country[433]",
			"value": "",
			"enabled": true
		},
		{
			"key": "Name[433]",
			"value": "",
			"enabled": true
		},
		{
			"key": "URL[433]",
			"value": "",
			"enabled": true
		},
		{
			"key": "Country[434]",
			"value": "",
			"enabled": true
		},
		{
			"key": "Name[434]",
			"value": "",
			"enabled": true
		},
		{
			"key": "URL[434]",
			"value": "",
			"enabled": true
		},
		{
			"key": "Country[435]",
			"value": "",
			"enabled": true
		},
		{
			"key": "Name[435]",
			"value": "",
			"enabled": true
		},
		{
			"key": "URL[435]",
			"value": "",
			"enabled": true
		},
		{
			"key": "Country[436]",
			"value": "",
			"enabled": true
		},
		{
			"key": "Name[436]",
			"value": "",
			"enabled": true
		},
		{
			"key": "URL[436]",
			"value": "",
			"enabled": true
		},
		{
			"key": "Country[437]",
			"value": "",
			"enabled": true
		},
		{
			"key": "Name[437]",
			"value": "",
			"enabled": true
		},
		{
			"key": "URL[437]",
			"value": "",
			"enabled": true
		},
		{
			"key": "Country[438]",
			"value": "",
			"enabled": true
		},
		{
			"key": "Name[438]",
			"value": "",
			"enabled": true
		},
		{
			"key": "URL[438]",
			"value": "",
			"enabled": true
		},
		{
			"key": "Country[439]",
			"value": "",
			"enabled": true
		},
		{
			"key": "Name[439]",
			"value": "",
			"enabled": true
		},
		{
			"key": "URL[439]",
			"value": "",
			"enabled": true
		},
		{
			"key": "Country[440]",
			"value": "",
			"enabled": true
		},
		{
			"key": "Name[440]",
			"value": "",
			"enabled": true
		},
		{
			"key": "URL[440]",
			"value": "",
			"enabled": true
		},
		{
			"key": "Country[441]",
			"value": "",
			"enabled": true
		},
		{
			"key": "Name[441]",
			"value": "",
			"enabled": true
		},
		{
			"key": "URL[441]",
			"value": "",
			"enabled": true
		},
		{
			"key": "Country[442]",
			"value": "",
			"enabled": true
		},
		{
			"key": "Name[442]",
			"value": "",
			"enabled": true
		},
		{
			"key": "URL[442]",
			"value": "",
			"enabled": true
		},
		{
			"key": "Country[443]",
			"value": "",
			"enabled": true
		},
		{
			"key": "Name[443]",
			"value": "",
			"enabled": true
		},
		{
			"key": "URL[443]",
			"value": "",
			"enabled": true
		},
		{
			"key": "Country[444]",
			"value": "",
			"enabled": true
		},
		{
			"key": "Name[444]",
			"value": "",
			"enabled": true
		},
		{
			"key": "URL[444]",
			"value": "",
			"enabled": true
		},
		{
			"key": "Country[445]",
			"value": "",
			"enabled": true
		},
		{
			"key": "Name[445]",
			"value": "",
			"enabled": true
		},
		{
			"key": "URL[445]",
			"value": "",
			"enabled": true
		},
		{
			"key": "Country[446]",
			"value": "",
			"enabled": true
		},
		{
			"key": "Name[446]",
			"value": "",
			"enabled": true
		},
		{
			"key": "URL[446]",
			"value": "",
			"enabled": true
		},
		{
			"key": "Country[447]",
			"value": "",
			"enabled": true
		},
		{
			"key": "Name[447]",
			"value": "",
			"enabled": true
		},
		{
			"key": "URL[447]",
			"value": "",
			"enabled": true
		},
		{
			"key": "Country[448]",
			"value": "",
			"enabled": true
		},
		{
			"key": "Name[448]",
			"value": "",
			"enabled": true
		},
		{
			"key": "URL[448]",
			"value": "",
			"enabled": true
		},
		{
			"key": "Country[449]",
			"value": "",
			"enabled": true
		},
		{
			"key": "Name[449]",
			"value": "",
			"enabled": true
		},
		{
			"key": "URL[449]",
			"value": "",
			"enabled": true
		},
		{
			"key": "Country[450]",
			"value": "",
			"enabled": true
		},
		{
			"key": "Name[450]",
			"value": "",
			"enabled": true
		},
		{
			"key": "URL[450]",
			"value": "",
			"enabled": true
		},
		{
			"key": "Country[451]",
			"value": "",
			"enabled": true
		},
		{
			"key": "Name[451]",
			"value": "",
			"enabled": true
		},
		{
			"key": "URL[451]",
			"value": "",
			"enabled": true
		},
		{
			"key": "Country[452]",
			"value": "",
			"enabled": true
		},
		{
			"key": "Name[452]",
			"value": "",
			"enabled": true
		},
		{
			"key": "URL[452]",
			"value": "",
			"enabled": true
		},
		{
			"key": "Country[453]",
			"value": "",
			"enabled": true
		},
		{
			"key": "Name[453]",
			"value": "",
			"enabled": true
		},
		{
			"key": "URL[453]",
			"value": "",
			"enabled": true
		},
		{
			"key": "Country[454]",
			"value": "",
			"enabled": true
		},
		{
			"key": "Name[454]",
			"value": "",
			"enabled": true
		},
		{
			"key": "URL[454]",
			"value": "",
			"enabled": true
		},
		{
			"key": "Country[455]",
			"value": "",
			"enabled": true
		},
		{
			"key": "Name[455]",
			"value": "",
			"enabled": true
		},
		{
			"key": "URL[455]",
			"value": "",
			"enabled": true
		},
		{
			"key": "Country[456]",
			"value": "",
			"enabled": true
		},
		{
			"key": "Name[456]",
			"value": "",
			"enabled": true
		},
		{
			"key": "URL[456]",
			"value": "",
			"enabled": true
		},
		{
			"key": "Country[457]",
			"value": "",
			"enabled": true
		},
		{
			"key": "Name[457]",
			"value": "",
			"enabled": true
		},
		{
			"key": "URL[457]",
			"value": "",
			"enabled": true
		},
		{
			"key": "Country[459]",
			"value": "",
			"enabled": true
		},
		{
			"key": "Name[459]",
			"value": "",
			"enabled": true
		},
		{
			"key": "URL[459]",
			"value": "",
			"enabled": true
		},
		{
			"key": "Country[460]",
			"value": "",
			"enabled": true
		},
		{
			"key": "Name[460]",
			"value": "",
			"enabled": true
		},
		{
			"key": "URL[460]",
			"value": "",
			"enabled": true
		},
		{
			"key": "Country[461]",
			"value": "",
			"enabled": true
		},
		{
			"key": "Name[461]",
			"value": "",
			"enabled": true
		},
		{
			"key": "URL[461]",
			"value": "",
			"enabled": true
		},
		{
			"key": "Country[462]",
			"value": "",
			"enabled": true
		},
		{
			"key": "Name[462]",
			"value": "",
			"enabled": true
		},
		{
			"key": "URL[462]",
			"value": "",
			"enabled": true
		},
		{
			"key": "Country[463]",
			"value": "",
			"enabled": true
		},
		{
			"key": "Name[463]",
			"value": "",
			"enabled": true
		},
		{
			"key": "URL[463]",
			"value": "",
			"enabled": true
		},
		{
			"key": "Country[464]",
			"value": "",
			"enabled": true
		},
		{
			"key": "Name[464]",
			"value": "",
			"enabled": true
		},
		{
			"key": "URL[464]",
			"value": "",
			"enabled": true
		},
		{
			"key": "Country[465]",
			"value": "",
			"enabled": true
		},
		{
			"key": "Name[465]",
			"value": "",
			"enabled": true
		},
		{
			"key": "URL[465]",
			"value": "",
			"enabled": true
		},
		{
			"key": "Country[466]",
			"value": "",
			"enabled": true
		},
		{
			"key": "Name[466]",
			"value": "",
			"enabled": true
		},
		{
			"key": "URL[466]",
			"value": "",
			"enabled": true
		}
	],
	"_postman_variable_scope": "environment",
	"_postman_exported_at": "2021-06-11T19:14:45.572Z",
	"_postman_exported_using": "Postman/8.6.1"
}